{"connections": [{"timestamp_connections": []}, {"timestamp_connections": []}, {"timestamp_connections": []}, {"timestamp_connections": []}, {"timestamp_connections": []}, {"timestamp_connections": []}, {"timestamp_connections": []}, {"timestamp_connections": []}, {"timestamp_connections": ["sevdehazan;hakanhasturk;1", "aylatfekigil;hbhaydarbas;1", "lutfullahonder;hbhaydarbas;1", "ilhanaydogdu;hbhaydarbas;1", "omertaskin42;hbhaydarbas;1", "meryemkcci;hbhaydarbas;1", "ehlibeytgunlugu;hbhaydarbas;1", "maydemir19;hbhaydarbas;1", "nuriosmanyilmaz;hbhaydarbas;1", "haydargenccan;hbhaydarbas;1", "taner9182;hbhaydarbas;1", "ahmetnurolu;hbhaydarbas;1", "berlinicmal;hbhaydarbas;1", "reyhan_1974;hbhaydarbas;1", "kesanlismail;hbhaydarbas;1", "46merve1;hbhaydarbas;1", "erganayse;hbhaydarbas;1", "ismailsalkovic;hbhaydarbas;1", "turkgencligi33;hbhaydarbas;1", "inciyldrm89;hbhaydarbas;1", "fethiyolcu;hbhaydarbas;1", "nurcan_sahin76;hbhaydarbas;1", "cavitozdogan;hbhaydarbas;1", "simal06;hbhaydarbas;1", "seyyitaliyaman;hbhaydarbas;2", "mehlikeerkii;hbhaydarbas;1", "yaseminkarlda;hbhaydarbas;1", "ftfurkantalay;hbhaydarbas;1", "ehm4ever;hbhaydarbas;1", "telmankahraman;hbhaydarbas;1", "yasemingenc_;hbhaydarbas;1", "cemalcintosun;hbhaydarbas;1", "nezihe_kk;hbhaydarbas;1", "btptrabzon;hbhaydarbas;1", "_hanci_;hbhaydarbas;1", "joseph_sinan;hbhaydarbas;1", "baszadeler;hbhaydarbas;1", "gokhanabdullah;hbhaydarbas;1", "omerturanilbey;hbhaydarbas;1", "akadirekim;hbhaydarbas;1", "muhammethayir;hbhaydarbas;1", "61haydar;hbhaydarbas;1", "h_demirtas;hbhaydarbas;1", "karabulutglsen;hbhaydarbas;1", "okanozturan;hbhaydarbas;1", "atasehiricmal;hbhaydarbas;1", "krcmusahaydar;hbhaydarbas;1", "mcobanoglum;hbhaydarbas;1", "haydar_bas;hbhaydarbas;1", "erkutia;hbhaydarbas;1", "s_hancer;hbhaydarbas;1", "fatmacenkf;hbhaydarbas;1", "kimdineydi;hbhaydarbas;1", "ali_gul_lale;hbhaydarbas;1", "renantuna;hbhaydarbas;1", "yasin140380;hbhaydarbas;1", "yrbeyazal;hbhaydarbas;1", "zerrinhekimoglu;hbhaydarbas;1", "ihmumcu;hbhaydarbas;1", "rsruhisari;hbhaydarbas;1", "icmal_genci;hbhaydarbas;1", "salimdizi;hbhaydarbas;1", "snzcrt;hbhaydarbas;1", "rahmanyucel;hbhaydarbas;1", "haydarakyavuzz;hbhaydarbas;1", "haydardereci;hbhaydarbas;1", "akaraguzel61;hbhaydarbas;1", "abdullahmu3;hbhaydarbas;1", "hbsinan;hbhaydarbas;1", "saruhan1973;hbhaydarbas;1", "medya_siyaset;hbhaydarbas;1", "kadiryucelll;hbhaydarbas;1", "azizim45;hbhaydarbas;1", "celmelikubra;hbhaydarbas;1", "chillibom;hbhaydarbas;1", "yanik_ferhat;hbhaydarbas;1", "ayseerkii;hbhaydarbas;1", "baldemir23;hbhaydarbas;1", "mnahit;hbhaydarbas;1", "ulumanhavva;hbhaydarbas;1", "recepparlak10;hbhaydarbas;1", "kececilhan;hbhaydarbas;1", "arslantuncay55;hbhaydarbas;1", "independent_tp;hbhaydarbas;1", "fm_aydin1;hbhaydarbas;1", "al0ne;hbhaydarbas;1", "mem_hb;hbhaydarbas;1", "zuhtukazanci;hbhaydarbas;1", "atfkcgl;hbhaydarbas;1", "altan_haydar;hbhaydarbas;1", "kadiremine;hbhaydarbas;1", "mimarbayram;hbhaydarbas;1", "osmantfekigil;hbhaydarbas;1", "capultasi;hbhaydarbas;1", "ecyadturk_ecyad;hbhaydarbas;1", "selcukevsan;hbhaydarbas;1", "abdulkadirkhrm;hbhaydarbas;1", "kadriyehayr;hbhaydarbas;1", "ummuhangncsln;hbhaydarbas;1", "mydalgic;hbhaydarbas;1", "merveaydin_61;hbhaydarbas;1", "nakibudak;hbhaydarbas;1", "btpist;hbhaydarbas;1", "caps_turk;hbhaydarbas;1", "muhammedkkeskin;hbhaydarbas;1", "samioymak68;hbhaydarbas;1", "mustafaerkii;hbhaydarbas;2", "sevdehazan;hbhaydarbas;1", "m10kose;hbhaydarbas;1", "erataemine73;hbhaydarbas;1", "btp_parti;hbhaydarbas;1", "farukberkkara;hbhaydarbas;1"]}, {"timestamp_connections": ["fth_irmak;hbhaydarbas;1", "zuhtukazanci;mem_hb;1", "znur59539356;icmalgencligi;1", "rstbstn;icmalgencligi;1", "btptrabzon;mem_hb;1", "cemalcintosun;mem_hb;1", "barisgovec;hbhaydarbas;1", "_latife__;icmalgencligi;1", "eahhm;mem_hb;1", "mestozkan;mem_hb;1", "h_marjnal;mem_hb;1", "berlinicmal;icmalgencligi;1", "zehraarisoy;btp_parti;1", "recepparlak10;btp_parti;1", "ksamet38;hbhaydarbas;1", "tomyanak;hbhaydarbas;1", "hbhaydarbaki;icmalgencligi;1", "ismailsalkovic;hbhaydarbas;1", "privotcik;mem_hb;1", "yildizusame;hbhaydarbas;1", "snzcrt;hbhaydarbas;1", "remzibaba2;hbhaydarbas;1", "hydrycl;hbhaydarbas;2", "28btphakan;btp_parti;1", "omertaskin42;hbhaydarbas;1", "mukremin1961;mem_hb;1", "omerturanilbey;mem_hb;1", "yrbeyazal;hbhaydarbas;1", "ecyadturk_ecyad;btp_parti;1", "h_marjnal;icmalgencligi;1", "hbhaydarbaki;mem_hb;1", "btp_parti;hbhaydarbas;1", "rsruhisari;btp_parti;1", "mnahit;mem_hb;1", "zeynepbasguden;icmalgencligi;1", "muhammethayir;icmalgencligi;1", "rsruhisari;hbhaydarbas;1", "zeynepbasguden;hbhaydarbas;2", "milletinefendi;hbhaydarbas;2", "aslankamer;meltemhaber;1", "glen_kamuran;mem_hb;1", "dkcmesut;btp_parti;1", "kimdineydi;hbhaydarbas;1", "ftfurkantalay;meltemhaber;1", "rahmanyucel;btp_parti;1", "altan_haydar;icmalgencligi;1", "dirgona;hbhaydarbas;1", "kimdineydi;icmalgencligi;1", "asiyeebru;mem_hb;1", "bayramo55;icmalgencligi;1", "burakhaydar61;btp_parti;1", "turkgencligi33;btp_parti;1", "asiyeebru;btp_parti;1", "kaleminkalbi;mem_hb;1", "barisgovec;icmalgencligi;1", "tcyatar;hbhaydarbas;1", "erenplt;mem_hb;1", "husamettince;icmalgencligi;1", "fethiyolcu;icmalgencligi;1", "kaleminkalbi;btp_parti;1", "zehraarisoy;meltemhaber;1", "mnahit;btp_parti;1", "28btphakan;icmalgencligi;1", "haydargenccan;hbhaydarbas;1", "altan_haydar;mem_hb;1", "zehraarisoy;icmalgencligi;1", "rahmanyucel;mem_hb;1", "978sedat;hbhaydarbas;1", "sturkoz1006;meltemhaber;1", "tubakaraca34;icmalgencligi;1", "dirgona;btp_parti;1", "fatselcuk;hbhaydarbas;1", "cemalcintosun;icmalgencligi;1", "ksamet38;icmalgencligi;1", "berlinicmal;mem_hb;1", "tubakaraca34;mem_hb;1", "recepparlak10;icmalgencligi;1", "omerturanilbey;btp_parti;1", "rsruhisari;icmalgencligi;1", "tubakaraca34;btp_parti;1", "burakhaydar61;hbhaydarbas;1", "atfkcgl;hbhaydarbas;1", "saruhan1973;hbhaydarbas;1", "kadiryucelll;icmalgencligi;1", "mukremin1961;icmalgencligi;1", "kip_tf;hbhaydarbas;1", "hakbey;meltemhaber;1", "burakhaydar61;icmalgencligi;1", "privotcik;icmalgencligi;1", "mem_hb;icmalgencligi;1", "barisgovec;btp_parti;1", "husamettince;hbhaydarbas;2", "_latife__;hbhaydarbas;1", "kaleminkalbi;icmalgencligi;1", "tubarana4;mem_hb;1", "aterzi58;btp_parti;1", "kadiryucelll;hbhaydarbas;1", "rahmanyucel;icmalgencligi;1", "fethiyolcu;mem_hb;1", "kimdineydi;btp_parti;1", "rstbstn;btp_parti;1", "aterzi58;hbhaydarbas;2", "28btphakan;hbhaydarbas;1", "zerrinhekimoglu;btp_parti;1", "mpmahmutpolat;hbhaydarbas;1", "ehm4ever;icmalgencligi;1", "omertaskin42;icmalgencligi;1", "yrbeyazal;icmalgencligi;1", "turkgencligi33;hbhaydarbas;1", "hbhaydarbaki;hbhaydarbas;1", "kececilhan;icmalgencligi;1", "karabulutglsen;btp_parti;1", "btp_parti;icmalgencligi;1", "mrdoan7;btp_parti;1", "fatselcuk;mem_hb;1", "znur59539356;mem_hb;1", "glen_kamuran;icmalgencligi;1", "barisgovec;mem_hb;1", "turhandemir;hbhaydarbas;2", "karabulutglsen;mem_hb;1", "ecyadturk_ecyad;mem_hb;1", "fethiyolcu;btp_parti;1", "independent_tp;btp_parti;1", "hydrycl;btp_parti;1", "asi00134;hbhaydarbas;1", "saruhan1973;btp_parti;1", "turhandemir;mem_hb;1", "fethiyolcu;hbhaydarbas;1", "asahin216;hbhaydarbas;1", "nurcan_sahin76;hbhaydarbas;1", "muhammethayir;hbhaydarbas;1", "snzcrt;btp_parti;1", "snzcrt;icmalgencligi;1", "yanik_ferhat;meltemhaber;1", "merkalem;btp_parti;2", "ismailsalkovic;icmalgencligi;1", "turhandemir;btp_parti;1", "erenplt;btp_parti;1", "dkcmesut;icmalgencligi;1", "zeynepbasguden;mem_hb;1", "mnahit;hbhaydarbas;1", "rstbstn;mem_hb;1", "yakupsivas;meltemhaber;1", "necla_asan;hbhaydarbas;1", "rahmanyucel;meltemhaber;1", "icmalgencligi;mem_hb;1", "bkaramus;hbhaydarbas;1", "recepparlak10;hbhaydarbas;1", "kececilhan;hbhaydarbas;1", "icmalgencligi;btp_parti;1", "recepparlak10;mem_hb;1", "btp_parti;mem_hb;1", "haydargenccan;btp_parti;1", "glen_kamuran;btp_parti;1", "fatselcuk;icmalgencligi;1", "karaguzelcom;meltemhaber;1", "turkgencligi33;icmalgencligi;1", "privotcik;btp_parti;1", "hbhaydarbaki;btp_parti;1", "ecyadturk_ecyad;icmalgencligi;1", "milletinefendi;icmalgencligi;1", "snzcrt;mem_hb;1", "dkcmesut;mem_hb;1", "independent_tp;hbhaydarbas;1", "bayramo55;mem_hb;1", "tepetas_serap;hbhaydarbas;1", "seyyah4732;meltemhaber;2", "independent_tp;icmalgencligi;1", "978sedat;icmalgencligi;1", "eahhm;hbhaydarbas;1", "tcyatar;mem_hb;1", "haydargenccan;mem_hb;1", "husamettince;mem_hb;1", "icmalbayrampasa;hbhaydarbas;1", "mestozkan;btp_parti;1", "milletinefendi;mem_hb;1", "kadiryucelll;btp_parti;1", "mem_hb;hbhaydarbas;1", "harunhaydar;hbhaydarbas;1", "ismailsalkovic;btp_parti;1", "savukduran1;hbhaydarbas;1", "ehm4ever;hbhaydarbas;1", "hbhaydarbas;btp_parti;1", "atfkcgl;mem_hb;1", "kadiryucelll;mem_hb;1", "kip_tf;mem_hb;1", "hbhaydarbas;icmalgencligi;1", "ecyadturk_ecyad;hbhaydarbas;1", "kimdineydi;mem_hb;1", "asiyeebru;hbhaydarbas;2", "rstbstn;hbhaydarbas;1", "drkadirgndz;hbhaydarbas;1", "saruhan1973;icmalgencligi;1", "omertaskin42;mem_hb;1", "haydargenccan;icmalgencligi;1", "bayramo55;btp_parti;1", "zuhtukazanci;hbhaydarbas;1", "erenplt;hbhaydarbas;2", "btptrabzon;icmalgencligi;1", "yrbeyazal;mem_hb;1", "selcukevsan;meltemhaber;1", "eahhm;btp_parti;1", "berlinicmal;btp_parti;1", "altan_haydar;hbhaydarbas;1", "znur59539356;hbhaydarbas;1", "tubarana4;btp_parti;1", "h_marjnal;btp_parti;1", "nurcan_sahin76;btp_parti;1", "milletinefendi;btp_parti;1", "mrdoan7;hbhaydarbas;2", "berlinicmal;hbhaydarbas;1", "yavuzekm;hbhaydarbas;1", "aterzi58;mem_hb;1", "btptrabzon;hbhaydarbas;1", "erenplt;icmalgencligi;1", "zuhtukazanci;icmalgencligi;1", "zerrinhekimoglu;hbhaydarbas;1", "muhammethayir;btp_parti;1", "omertaskin42;btp_parti;1", "privotcik;hbhaydarbas;2", "zeynepbasguden;btp_parti;1", "ydyuksel;mem_hb;1", "kip_tf;btp_parti;1", "ydyuksel;btp_parti;1", "mukremin1961;hbhaydarbas;2", "dirgona;mem_hb;1", "h_marjnal;hbhaydarbas;1", "karabulutglsen;icmalgencligi;1", "turkgencligi33;mem_hb;1", "saruhan1973;mem_hb;1", "sonerhanife;meltemhaber;1", "mrdoan7;icmalgencligi;1", "henginkaya;meltemhaber;1", "turhandemir;icmalgencligi;1", "rsruhisari;mem_hb;1", "mstfagngr0606;hbhaydarbas;1", "mrdoan7;mem_hb;1", "nurcan_sahin76;mem_hb;1", "mestozkan;hbhaydarbas;1", "ksamet38;mem_hb;1", "978sedat;mem_hb;1", "merkalem;hbhaydarbas;2", "mukremin1961;btp_parti;1", "tubakaraca34;hbhaydarbas;1", "altan_haydar;btp_parti;1", "merkalem;mem_hb;2", "tubarana4;hbhaydarbas;1", "ksamet38;btp_parti;1", "_latife__;btp_parti;1", "ydyuksel;icmalgencligi;1", "tubarana4;icmalgencligi;1", "omerturanilbey;hbhaydarbas;1", "caps_turk;icmalgencligi;1", "znur59539356;btp_parti;1", "nurcan_sahin76;icmalgencligi;1", "978sedat;btp_parti;1", "hydrycl;mem_hb;1", "glen_kamuran;hbhaydarbas;1", "tcyatar;btp_parti;1", "ismailsalkovic;mem_hb;1", "dkcmesut;hbhaydarbas;1", "muhammethayir;mem_hb;1", "btp_parti;meltemhaber;1", "asiyeebru;icmalgencligi;1", "zerrinhekimoglu;icmalgencligi;1", "hydrycl;icmalgencligi;1", "caps_turk;hbhaydarbas;1", "mrdoan7;meltemhaber;1", "zuhtukazanci;btp_parti;1", "caps_turk;mem_hb;1", "husamettince;btp_parti;1", "rahmanyucel;hbhaydarbas;1", "zerrinhekimoglu;mem_hb;1", "mem_hb;btp_parti;1", "atfkcgl;icmalgencligi;1", "btptrabzon;btp_parti;1", "kaleminkalbi;hbhaydarbas;1", "bkaramus;icmalgencligi;1", "zehraarisoy;mem_hb;1", "omerturanilbey;icmalgencligi;1", "zehraarisoy;hbhaydarbas;1", "nurcan_sahin76;meltemhaber;1", "tcyatar;icmalgencligi;1", "karabulutglsen;hbhaydarbas;1", "icmalgencligi;hbhaydarbas;2", "kececilhan;mem_hb;1", "ehm4ever;btp_parti;1", "yrbeyazal;btp_parti;1", "cemalcintosun;hbhaydarbas;1", "dirgona;icmalgencligi;1", "cemalcintosun;btp_parti;1", "caps_turk;btp_parti;1", "eahhm;icmalgencligi;1", "bayramo55;hbhaydarbas;1", "mestozkan;icmalgencligi;1", "mnahit;icmalgencligi;1", "omerturanilbey;meltemhaber;1", "28btphakan;mem_hb;1", "ydyuksel;hbhaydarbas;2", "aterzi58;icmalgencligi;1", "independent_tp;mem_hb;1", "bkaramus;btp_parti;1", "fatselcuk;btp_parti;1", "ehm4ever;mem_hb;1", "bkaramus;mem_hb;1", "burakhaydar61;mem_hb;1", "kececilhan;btp_parti;1", "kip_tf;icmalgencligi;1", "merkalem;icmalgencligi;2", "hbhaydarbas;mem_hb;1", "_latife__;mem_hb;1"]}], "datasetInfo": {"allUsernames": [{"avatar": "http://pbs.twimg.com/profile_images/2649552689/40692c3f1282a21c812072fbf45ac2bf.png", "description": "", "followers_count": 175, "friends_count": 276, "id": 736887284, "listed_count": 0, "location": "", "name": "Hakan Kaya", "screen_name": "28btphakan", "statuses_count": 1246}, {"avatar": "http://pbs.twimg.com/profile_images/416384648940625920/3vVMH5-j.jpeg", "description": "", "followers_count": 154, "friends_count": 204, "id": 1443093864, "listed_count": 0, "location": "", "name": "MERVE", "screen_name": "46merve1", "statuses_count": 1725}, {"avatar": "http://pbs.twimg.com/profile_images/430692720097894400/W_H5pIb_.jpeg", "description": "Prof.Dr.Haydar Ba\u015f ve Trabzon sevdal\u0131s\u0131 - \u0130K\u00dc Hukuk okuyor - Avukat aday aday\u0131", "followers_count": 949, "friends_count": 196, "id": 624712038, "listed_count": 0, "location": "", "name": "Haydar Ergan", "screen_name": "61haydar", "statuses_count": 3334}, {"avatar": "http://pbs.twimg.com/profile_images/588177955827879936/RPjTwQCj.jpg", "description": "dobra konu\u015fmay\u0131 seven, kul hakk\u0131na dikkat eden, elektrik ve su faturalar\u0131na isyan eden, takip edeni takip edenim.", "followers_count": 861, "friends_count": 1868, "id": 1446305456, "listed_count": 0, "location": "", "name": "TCHB", "screen_name": "978sedat", "statuses_count": 6833}, {"avatar": "http://pbs.twimg.com/profile_images/592316349302624257/x0SD29XY.jpg", "description": "", "followers_count": 316, "friends_count": 1857, "id": 97178545, "listed_count": 1, "location": "", "name": "MetiN", "screen_name": "_hanci_", "statuses_count": 1493}, {"avatar": "http://pbs.twimg.com/profile_images/671399228627771392/qovW7wWj.jpg", "description": "HB|\u0130cmal Genci|Mustafa Kemal Atat\u00fcrk|Fenerbah\u00e7e|sagopakajmer", "followers_count": 1174, "friends_count": 1114, "id": 310412665, "listed_count": 1, "location": "Y\u0131ld\u0131r\u0131m, Bursa", "name": "\u00b0\u2022\u0130n\u015firah\u00b0\u2022", "screen_name": "_latife__", "statuses_count": 730}, {"avatar": "http://pbs.twimg.com/profile_images/569232060230156288/KNt11LC4.jpeg", "description": "", "followers_count": 527, "friends_count": 140, "id": 395467660, "listed_count": 0, "location": "istanbul-trabzon ", "name": "abdulkadir kahraman", "screen_name": "abdulkadirkhrm", "statuses_count": 3958}, {"avatar": "http://pbs.twimg.com/profile_images/451741436854407168/OEZQbufV.jpeg", "description": "Bu Vatan Bizimdir Bizim Kalacak. \nHer rt etti\u011fim onayl\u0131yorum anlam\u0131na gelmez.", "followers_count": 103, "friends_count": 478, "id": 1553589798, "listed_count": 0, "location": "", "name": "Abdullah Mu\u015f", "screen_name": "abdullahmu3", "statuses_count": 803}, {"avatar": "http://pbs.twimg.com/profile_images/3611504079/1384204c50ca09ccd04b71a92bb8d948.jpeg", "description": "Tarih?i, yazar", "followers_count": 318, "friends_count": 432, "id": "331673951", "listed_count": 0, "location": "Adana", "name": "Ahmet Nuro?lu", "screen_name": "ahmetnurolu", "statuses_count": 4331}, {"avatar": "http://pbs.twimg.com/profile_images/3741887305/65f631b577fca4aec7e826e577a4ff2b.jpeg", "description": "", "followers_count": 932, "friends_count": 481, "id": 1475305334, "listed_count": 2, "location": "", "name": "Abd\u00fclkadir Ekim", "screen_name": "akadirekim", "statuses_count": 19978}, {"avatar": "http://pbs.twimg.com/profile_images/1766202464/akg.jpg", "description": "\u0130lahiyat\u00e7\u0131, E\u011fitimci, Kuvvay\u0131 Milliyeci,\nEhli Beyt Taraftar\u0131, Ba\u015far\u0131l\u0131 Koleji, Trabzonspor, \u0130cmal Gen\u00e7li\u011fi", "followers_count": 349, "friends_count": 159, "id": 151094346, "listed_count": 0, "location": "", "name": "AHMET KARAG\u00dcZEL", "screen_name": "akaraguzel61", "statuses_count": 1255}, {"avatar": "http://pbs.twimg.com/profile_images/531834739527659520/JZHD-A36.jpeg", "description": "K\u00f6t\u00fc,Kaba,Terbiyesiz", "followers_count": 1994, "friends_count": 1304, "id": 11530472, "listed_count": 5, "location": "", "name": "byTekin", "screen_name": "al0ne", "statuses_count": 35787}, {"avatar": "http://pbs.twimg.com/profile_images/575791481010716672/U9zDAN90.jpeg", "description": "", "followers_count": 0, "friends_count": 66, "id": 1575202386, "listed_count": 0, "location": "", "name": "Ali G\u00fcl", "screen_name": "ali_gul_lale", "statuses_count": 7}, {"avatar": "http://pbs.twimg.com/profile_images/532239998868008960/tm14LhjD.jpeg", "description": "", "followers_count": 476, "friends_count": 787, "id": 1533121922, "listed_count": 0, "location": "", "name": "haydar altan", "screen_name": "altan_haydar", "statuses_count": 1077}, {"avatar": "http://pbs.twimg.com/profile_images/539834418278694912/kuo29HBW.jpeg", "description": "", "followers_count": 62, "friends_count": 252, "id": 2900871987, "listed_count": 0, "location": "", "name": "Arslan Tun\u00e7ay", "screen_name": "arslantuncay55", "statuses_count": 371}, {"avatar": "http://pbs.twimg.com/profile_images/3666386343/fdd06fa75533e0220e9003145b85a65e.jpeg", "description": "Eden kendine eder, Yapan bulur ve \u00e7eker, unutma kazanmak koca bir \u00f6m\u00fcr ister.Kaybetmeye ise anl\u0131k  gaflet yeter.Hz.mevlana...", "followers_count": 463, "friends_count": 157, "id": 1432415214, "listed_count": 0, "location": "", "name": "Ahmet \u015eahin", "screen_name": "asahin216", "statuses_count": 8680}, {"avatar": "http://abs.twimg.com/sticky/default_profile_images/default_profile_2.png", "description": null, "followers_count": 11, "friends_count": 42, "id": "3003026476", "listed_count": 0, "location": "", "name": "Fat?ma", "screen_name": "asi00134", "statuses_count": 3}, {"avatar": "http://pbs.twimg.com/profile_images/575289972053442560/3Z3Qyaak.jpeg", "description": "", "followers_count": 136, "friends_count": 178, "id": 1445459196, "listed_count": 2, "location": "", "name": "Asiye Ebru Dede", "screen_name": "asiyeebru", "statuses_count": 2253}, {"avatar": "http://pbs.twimg.com/profile_images/680352127416446977/xR_ieYyq.jpg", "description": "Program yap\u0131mc\u0131s\u0131 & seslendirmen,\n[Parantez] H.i\u00e7i 12.30'da Meltem TV'de,\nYeni Mesaj Gazetesi'nde Yazar,\nhttps://t.co/DOWnQS0vL0 y\u00f6netici&yap\u0131mc\u0131", "followers_count": 394, "friends_count": 413, "id": 1573201255, "listed_count": 3, "location": "\u0130stanbul Program yap\u0131mc\u0131s\u0131 & s", "name": "Aslan Kamer", "screen_name": "aslankamer", "statuses_count": 2789}, {"avatar": "http://pbs.twimg.com/profile_images/551792373223931904/yMdg_qFG.jpeg", "description": "Birlikte rahmet ayr\u0131l\u0131kta azap vard\u0131r..", "followers_count": 621, "friends_count": 882, "id": 2960532472, "listed_count": 0, "location": "Ata\u015fehir", "name": "BTP Ata\u015fehir Gen\u00e7lik", "screen_name": "atasehiricmal", "statuses_count": 1734}, {"avatar": "http://pbs.twimg.com/profile_images/3681159596/33f11246e3f118f87bf9fc2d78d9ed04.jpeg", "description": "", "followers_count": 5118, "friends_count": 208, "id": 1431502579, "listed_count": 2, "location": "", "name": "Dr.Abdullah Terzi", "screen_name": "aterzi58", "statuses_count": 2829}, {"avatar": "http://pbs.twimg.com/profile_images/586232911571058688/PCTN9tUm.jpg", "description": "", "followers_count": 36, "friends_count": 11, "id": 2748228821, "listed_count": 0, "location": "", "name": "Ayla Tfkcgl", "screen_name": "atfkcgl", "statuses_count": 1474}, {"avatar": "http://pbs.twimg.com/profile_images/586233141305696256/-kewP9n-.jpg", "description": "", "followers_count": 495, "friends_count": 55, "id": 1446977288, "listed_count": 0, "location": "", "name": "Ayla G\u00f6ksel", "screen_name": "aylatfekigil", "statuses_count": 5993}, {"avatar": "http://pbs.twimg.com/profile_images/586233453487751169/otWVgJ0F.jpg", "description": "BU VATAN B\u0130Z\u0130MD\u0130R B\u0130Z\u0130M KALACAK", "followers_count": 133, "friends_count": 7, "id": 1451073540, "listed_count": 0, "location": "", "name": "ay\u015fe erkisi", "screen_name": "ayseerkii", "statuses_count": 2211}, {"avatar": "http://pbs.twimg.com/profile_images/591687368089935872/8H2K9JQs.png", "description": "insan g\u00f6n\u00fcld\u00fcr g\u00f6n\u00fcl", "followers_count": 748, "friends_count": 200, "id": 1231327777, "listed_count": 2, "location": "", "name": "Aziz usta", "screen_name": "azizim45", "statuses_count": 25818}, {"avatar": "http://pbs.twimg.com/profile_images/592977035548610560/mEJsVsZr.jpg", "description": "", "followers_count": 38, "friends_count": 191, "id": 2563749245, "listed_count": 0, "location": "", "name": "\u00f6nce Vatan", "screen_name": "baldemir23", "statuses_count": 559}, {"avatar": "http://pbs.twimg.com/profile_images/606054634818564096/CjwemgQ-.jpg", "description": "", "followers_count": 389, "friends_count": 284, "id": 176159494, "listed_count": 0, "location": "Kayseri", "name": "Bar\u0131\u015f G\u00f6ve\u00e7", "screen_name": "barisgovec", "statuses_count": 30}, {"avatar": "http://pbs.twimg.com/profile_images/430467195840126976/q1MXOxXW.png", "description": "Ba\u015fZadeler Butik Resmi Twitter Hesab\u0131 Sadece Size \u00d6zel TEL:0462 228 40 20", "followers_count": 1509, "friends_count": 16, "id": 2326099332, "listed_count": 2, "location": "", "name": "BA\u015eZADELER", "screen_name": "baszadeler", "statuses_count": 271}, {"avatar": "http://pbs.twimg.com/profile_images/378800000010611168/06d0d7cf16b5d2ca53cd0c4746b4ecd1.jpeg", "description": "", "followers_count": 1545, "friends_count": 636, "id": 1432759777, "listed_count": 1, "location": "", "name": "Bayram \u00d6zdemir", "screen_name": "bayramo55", "statuses_count": 7843}, {"avatar": "http://pbs.twimg.com/profile_images/602405102666829824/-fuYjjC5.jpg", "description": "Haydarizm - \u0130cmal Gen\u00e7i - MEM - MeltemTv - Yeni Mesaj - Hakk'a ko\u015fun, Hakk'la olun, hakl\u0131 ile olun, hakl\u0131 olun. Hepiniz Hakk'a emanet olun.. Prof.Dr. Haydar Ba\u015f", "followers_count": 490, "friends_count": 213, "id": 1475635844, "listed_count": 0, "location": "Berlin", "name": "Rabia Karakurt", "screen_name": "berlinicmal", "statuses_count": 3896}, {"avatar": "http://pbs.twimg.com/profile_images/459796128113131521/hCH9Wrc2.jpeg", "description": "", "followers_count": 12212, "friends_count": 95, "id": 1438052347, "listed_count": 2, "location": "", "name": "Bilal KARAMUS", "screen_name": "bkaramus", "statuses_count": 659}, {"avatar": "http://pbs.twimg.com/profile_images/3157774166/c48be8fc3445aa83a7608d6e2b7b78d3.jpeg", "description": "Ba\u011f\u0131ms\u0131z T\u00fcrkiye Partisi #BTP \u2022 Resmi twitter sayfas\u0131 \u2022 http://t.co/xUkLcoqNwH \u2022 http://t.co/XkoR70JOZ9", "followers_count": 13274, "friends_count": 6, "id": 1117451995, "listed_count": 11, "location": "T\u00fcrkiye", "name": "Ba\u011f\u0131ms\u0131zT\u00fcrkiyeParti", "screen_name": "btp_parti", "statuses_count": 789}, {"avatar": "http://pbs.twimg.com/profile_images/593179257477668865/XeUowGJO.jpg", "description": "", "followers_count": 454, "friends_count": 204, "id": 426134392, "listed_count": 1, "location": "T\u00dcRK\u0130YE", "name": "Kur\u015fun-i Renkler", "screen_name": "btpist", "statuses_count": 6620}, {"avatar": "http://pbs.twimg.com/profile_images/3690411844/ee5b918f2823c816c8a65d3ce0d42c3d.png", "description": "Ba??ms?z T?rkiye Partisi (BTP)", "followers_count": 1399, "friends_count": 1331, "id": "1446605970", "listed_count": 0, "location": "Trabzon,T?rkiye", "name": "BTP Trabzon", "screen_name": "btptrabzon", "statuses_count": 2473}, {"avatar": "http://pbs.twimg.com/profile_images/472467006126448641/T5WS4Jp0.jpeg", "description": "KORKMAZ \u0130BRAH\u0130M OLAN, NEMRUT'U ATE\u015e\u0130NDEN!", "followers_count": 253, "friends_count": 246, "id": 1446152923, "listed_count": 0, "location": "Ankara", "name": "burak karata\u015fo\u011flu", "screen_name": "burakhaydar61", "statuses_count": 2898}, {"avatar": "http://pbs.twimg.com/profile_images/606620846350823424/nmIvlkut.jpg", "description": "Prof. Dr. Haydar Ba\u015f - Mustafa Kemal Atat\u00fcrk", "followers_count": 643, "friends_count": 381, "id": 2347002350, "listed_count": 0, "location": "T\u00fcrkiye", "name": "\u00d6lene Kadar !", "screen_name": "caps_turk", "statuses_count": 2084}, {"avatar": "http://pbs.twimg.com/profile_images/378800000838226562/dd9c6dbeb6348caaa7bb1a06749b6119.jpeg", "description": "GG", "followers_count": 1691, "friends_count": 121, "id": 455051853, "listed_count": 0, "location": "\u0130zmir - \u0130stanbul", "name": "HAYDAR\u0130", "screen_name": "capultasi", "statuses_count": 3436}, {"avatar": "http://pbs.twimg.com/profile_images/582277592469893120/Lj99rriz.jpg", "description": "Bitkisel Tedavi uzmanlar\u0131yla Tv Programlar\u0131 yap\u0131yor. \u0130yile\u015fen binlerce hastan\u0131n sa\u011fl\u0131k \u00f6yk\u00fclerini ekranlara ta\u015f\u0131yor. Panax'\u0131 \u00f6neriyor (Taklitlerinden sak\u0131n\u0131n)", "followers_count": 1229, "friends_count": 169, "id": 548309529, "listed_count": 0, "location": "\u0130stanbul", "name": "\u00d6nce Vatan...", "screen_name": "cavitozdogan", "statuses_count": 6976}, {"avatar": "http://pbs.twimg.com/profile_images/534393579817295872/umNxfa8y.jpeg", "description": "U?-S?n?f ??retmenli?i/ ESOG?", "followers_count": 61, "friends_count": 46, "id": "2881336852", "listed_count": 0, "location": "????? ???????", "name": "K?bra ?elmeli", "screen_name": "celmelikubra", "statuses_count": 244}, {"avatar": "http://pbs.twimg.com/profile_images/637590498832723968/QS4S2U8n.jpg", "description": "Siyasi twettciler Ak partisini hep ele\u015ftiriler; ama nedense, BOP'tan B\u00fcy\u00fck \u0130srail Devletinden bahsetmezler. Acaba biz daha iyimi yapar\u0131z diyorlar.", "followers_count": 337, "friends_count": 239, "id": 409364485, "listed_count": 1, "location": "", "name": "Cml Cntsn", "screen_name": "cemalcintosun", "statuses_count": 13008}, {"avatar": "http://pbs.twimg.com/profile_images/642127265766240256/_jtWfDyC.jpg", "description": "******** Stand up! This is your life ******** Yalanlara son veriyoruz. PKK'nin yapt\u0131\u011f\u0131 ve \u00fcstlendi\u011fi eylemleri kan\u0131tlarla veriyoruz.", "followers_count": 1160, "friends_count": 460, "id": 823464854, "listed_count": 4, "location": "M\u0130T/J\u0130TEM de\u011fil, PKK \u00fcstlendi", "name": "Chilli Bom", "screen_name": "chillibom", "statuses_count": 42708}, {"avatar": "http://pbs.twimg.com/profile_images/3666884147/d116c3785306173976a80ab62b584dc5.jpeg", "description": "Sahipsiz vatan\u0131n batmas\u0131 hakt\u0131r\r\nSen sahip \u00e7\u0131karsan bu vatan batmayacakt\u0131r", "followers_count": 9545, "friends_count": 6879, "id": 1432776391, "listed_count": 1, "location": "merkez", "name": "ba\u015ft\u00fcrk", "screen_name": "dirgona", "statuses_count": 3101}, {"avatar": "http://pbs.twimg.com/profile_images/592316514117820417/7otFxTrc.jpg", "description": "", "followers_count": 168, "friends_count": 41, "id": 1830025453, "listed_count": 0, "location": "", "name": "MESUT D\u0130K\u0130C\u0130", "screen_name": "dkcmesut", "statuses_count": 754}, {"avatar": "http://pbs.twimg.com/profile_images/378800000749325613/aef2ca4d3ba36bfc35f0cd221cd2725a.jpeg", "description": "", "followers_count": 742, "friends_count": 129, "id": 240337194, "listed_count": 1, "location": "", "name": "Kadir G\u00fcnd\u00fcz", "screen_name": "drkadirgndz", "statuses_count": 3947}, {"avatar": "http://pbs.twimg.com/profile_images/378800000610624115/59aa0e0c05c9e1eea4d26d811bfff14a.jpeg", "description": "ampul-e de\u011fil G\u00dcNE\u015eE bak\u0131yor", "followers_count": 96, "friends_count": 171, "id": 460238061, "listed_count": 0, "location": "", "name": "Handan  Altunb\u00fcker", "screen_name": "eahhm", "statuses_count": 309}, {"avatar": "http://pbs.twimg.com/profile_images/606001362749542400/ZX3rL8kr.jpg", "description": "Ehli Beyt A\u015fiklarina Selam", "followers_count": 7214, "friends_count": 8110, "id": 1525909694, "listed_count": 7, "location": "G.Mustafa Kemal", "name": "Ecyad", "screen_name": "ecyadturk_ecyad", "statuses_count": 11204}, {"avatar": "http://pbs.twimg.com/profile_images/509218957946290176/XM06Rbsr.jpeg", "description": "De ki (Muhammedim): Ben, peygamberli\u011fimi tebli\u011fime kar\u015f\u0131l\u0131k sizden, Ehl-i Beytimi sevmenizden ba\u015fka hi\u00e7bir \u00fccret istemiyorum.(\u015eura, 23)", "followers_count": 6657, "friends_count": 3966, "id": 2765287089, "listed_count": 1, "location": "", "name": "Ehl-i Beyt", "screen_name": "ehlibeytgunlugu", "statuses_count": 1791}, {"avatar": "http://pbs.twimg.com/profile_images/681444463089205248/OuTy9Bj2.jpg", "description": "#EHM4ever", "followers_count": 1413, "friends_count": 43, "id": 2919877384, "listed_count": 0, "location": "", "name": "Mehmet Fatih ERATA", "screen_name": "ehm4ever", "statuses_count": 15}, {"avatar": "http://pbs.twimg.com/profile_images/378800000377536183/950628277fa2a0226ac6ae64a7eb0ab7.jpeg", "description": "zonguldak l\u0131 BTP sevdal\u0131s\u0131", "followers_count": 397, "friends_count": 440, "id": 1454490139, "listed_count": 0, "location": "", "name": "Emine Erata", "screen_name": "erataemine73", "statuses_count": 3421}, {"avatar": "http://pbs.twimg.com/profile_images/3628682635/e55bc65777e971e567d318b1134380f0.jpeg", "description": null, "followers_count": 87, "friends_count": 93, "id": "311660360", "listed_count": 0, "location": "istanbul ", "name": "Eren Polat", "screen_name": "erenplt", "statuses_count": 495}, {"avatar": "http://pbs.twimg.com/profile_images/523960629523415040/vl5GPxcT.jpeg", "description": "", "followers_count": 743, "friends_count": 166, "id": 1442245596, "listed_count": 0, "location": "", "name": "Ay\u015fe Ergan", "screen_name": "erganayse", "statuses_count": 1077}, {"avatar": "http://pbs.twimg.com/profile_images/571244894425849856/uJouDzQx.jpeg", "description": "Fikri H\u00fcr Vicdan\u0131 H\u00fcr  Atat\u00fcrk Gibi T\u00fcrk Milliyet\u00e7isi", "followers_count": 1724, "friends_count": 1552, "id": 603381484, "listed_count": 10, "location": "", "name": " erkut \u263e\u2606 T.C.", "screen_name": "erkutia", "statuses_count": 20154}, {"avatar": "http://pbs.twimg.com/profile_images/3588204991/46bc68518c517d425b3471d1501d1e29.jpeg", "description": "TV MEDYA E\u011e\u0130T\u0130M", "followers_count": 2699, "friends_count": 782, "id": 380582447, "listed_count": 1, "location": "FLORYA", "name": "faruk karatay", "screen_name": "farukberkkara", "statuses_count": 8840}, {"avatar": "http://pbs.twimg.com/profile_images/677225820943970306/M2QHkatI.jpg", "description": "HBA", "followers_count": 100, "friends_count": 58, "id": 2210575896, "listed_count": 0, "location": "Malatya", "name": "Fat\u0131ma cenk", "screen_name": "fatmacenkf", "statuses_count": 1518}, {"avatar": "http://pbs.twimg.com/profile_images/637220312002756609/mk2KZeQd.jpg", "description": "", "followers_count": 35, "friends_count": 87, "id": 2845021511, "listed_count": 0, "location": "Bal\u0131kesir", "name": "Fat\u0131ma Sel\u00e7uk", "screen_name": "fatselcuk", "statuses_count": 742}, {"avatar": "http://pbs.twimg.com/profile_images/482867863989288960/IvLPbyE2.jpeg", "description": "", "followers_count": 44, "friends_count": 84, "id": 1449408024, "listed_count": 0, "location": "", "name": "Fethi Bayram Yolcu", "screen_name": "fethiyolcu", "statuses_count": 594}, {"avatar": "http://pbs.twimg.com/profile_images/614009713060114432/sz-NTODl.jpg", "description": "", "followers_count": 96, "friends_count": 117, "id": 2362572428, "listed_count": 0, "location": "", "name": "fatihmehmet ayd\u0131n", "screen_name": "fm_aydin1", "statuses_count": 831}, {"avatar": "http://pbs.twimg.com/profile_images/528321706075889665/BzAM6NXR.jpeg", "description": "Ehl-i Beyt; Atat?rk;Prof.Dr.Haydar Ba?;?cmal Gen?li?i;BTP?STGN?-?stanbul;Trabzon;1991;1947;61", "followers_count": 549, "friends_count": 61, "id": "1285957152", "listed_count": 1, "location": "", "name": "FURKAN TALAY", "screen_name": "ftfurkantalay", "statuses_count": 7540}, {"avatar": "http://pbs.twimg.com/profile_images/631946142239039488/aNb14fjn.jpg", "description": "Kendimden,kendime..", "followers_count": 494, "friends_count": 341, "id": 602813925, "listed_count": 0, "location": "", "name": "Fatih Irmak", "screen_name": "fth_irmak", "statuses_count": 1747}, {"avatar": "http://pbs.twimg.com/profile_images/582991301777469440/P7TnCCLr.jpg", "description": "", "followers_count": 311, "friends_count": 257, "id": 1448527514, "listed_count": 4, "location": "", "name": "Kamuran G\u00fclen", "screen_name": "glen_kamuran", "statuses_count": 16536}, {"avatar": "http://pbs.twimg.com/profile_images/3723740801/9e23199c278de7c201786b44cc287eef.jpeg", "description": "", "followers_count": 17, "friends_count": 45, "id": 1449363764, "listed_count": 0, "location": "", "name": "Abdullah G\u00f6khan", "screen_name": "gokhanabdullah", "statuses_count": 319}, {"avatar": "http://pbs.twimg.com/profile_images/378800000056062107/cf5b04870312c8857be6dba075abcd47.jpeg", "description": "Bir T\u00fcrk bir d\u00fcnyaya bedeldir. Prof. Dr. Haydar Ba\u015f bin d\u00fcnyaya bedeldir.", "followers_count": 1237, "friends_count": 1681, "id": 280143569, "listed_count": 2, "location": "", "name": "KainatSeniBekliyor", "screen_name": "h_demirtas", "statuses_count": 7773}, {"avatar": "http://pbs.twimg.com/profile_images/590137523277553664/xWS-8WQE.jpg", "description": "Bu, teorideki kelebe\u011fin kanat \u00e7\u0131rp\u0131\u015f\u0131d\u0131r Political Science and International Relations\nBE\u015e\u0130KTA\u015e/\u0130STANBUL", "followers_count": 487, "friends_count": 271, "id": 1451756574, "listed_count": 0, "location": "", "name": "HTC", "screen_name": "h_marjnal", "statuses_count": 16630}, {"avatar": "http://pbs.twimg.com/profile_images/573759640892149760/trsguF0l.png", "description": "T\u00fcrk o\u011flu T\u00fcrk. Sanat ve Siyasetle ilgilenir. H\u0131rs\u0131zlar ve Vatan Hainleri uzak dursun...", "followers_count": 1672, "friends_count": 26, "id": 2354663425, "listed_count": 3, "location": "\u0130zmir", "name": "Hakan Hast\u00fcrk", "screen_name": "hakanhasturk", "statuses_count": 14360}, {"avatar": "http://pbs.twimg.com/profile_images/1780933655/n1288269026_30110389_9514.jpg", "description": "bayra?a sanca?a millete askere ve vatana Sahip ??kan ??heda namzetleri olal?m.haydar Ba?", "followers_count": 134, "friends_count": 185, "id": "159527789", "listed_count": 0, "location": "mardin/t?rkiye", "name": "h?d?r akbey", "screen_name": "hakbey", "statuses_count": 116}, {"avatar": "http://pbs.twimg.com/profile_images/514425596001398784/9Wbp1Wxk.jpeg", "description": "", "followers_count": 139, "friends_count": 68, "id": 385960174, "listed_count": 0, "location": "", "name": "Harun  Sofuo\u011flu", "screen_name": "harunhaydar", "statuses_count": 916}, {"avatar": "http://pbs.twimg.com/profile_images/378800000016092134/6fe003babd9e141ba8d8361ea863767b.jpeg", "description": "Bu sayfa Haydar Ba\u015f hayranlarina aittir.. B\u0130R BE\u015e\u0130KTA\u015e, B\u0130R HAYDAR BA\u015e GER\u0130S\u0130 TRA\u015e..EHL-\u0130 BEYT- HZ AL\u0130 -Diren T\u00fcrkiye-Diren \u00c7ar\u015f\u0131. Ya\u015fas\u0131n Ba\u011f\u0131ms\u0131z T\u00fcrkiye.", "followers_count": 3246, "friends_count": 602, "id": 220329058, "listed_count": 1, "location": "", "name": "HAYDAR BA\u015e S\u00d6ZLER\u0130", "screen_name": "haydar_bas", "statuses_count": 1371}, {"avatar": "http://pbs.twimg.com/profile_images/559797759788986368/0yDBiJV2.jpeg", "description": "BA?IMSIZ T?RK?YE PART?S? (BTP) BAYRAMPA?A GEN?LIK KOLLARI B?K. - ?ANLIURFA - SAL 2.SINIF - ICMAL GEN?L??? - M.K.ATAT?RK @HBhaydarbas", "followers_count": 1937, "friends_count": 1747, "id": "1029064915", "listed_count": 0, "location": "?STANBUL", "name": "Haydar Akyavuz", "screen_name": "haydarakyavuzz", "statuses_count": 4470}, {"avatar": "http://pbs.twimg.com/profile_images/550794931309408259/Yi7cAAkY.jpeg", "description": "Rahat ol...", "followers_count": 421, "friends_count": 62, "id": "251339471", "listed_count": 0, "location": "TRABZON", "name": "Haydar Dereci ", "screen_name": "haydardereci", "statuses_count": 1016}, {"avatar": "http://pbs.twimg.com/profile_images/663498642150531072/X3hjwbLc.jpg", "description": "Architect & Interior Designer", "followers_count": 1071, "friends_count": 100, "id": 1679948790, "listed_count": 0, "location": "Trabzon / T\u00dcRK\u0130YE", "name": "Haydar Gen\u00e7can", "screen_name": "haydargenccan", "statuses_count": 2245}, {"avatar": "http://pbs.twimg.com/profile_images/3781784028/6ce345690df96e0207160a861619dc22.png", "description": "", "followers_count": 384, "friends_count": 260, "id": 1446848654, "listed_count": 0, "location": "", "name": "HbHaydar Baki", "screen_name": "hbhaydarbaki", "statuses_count": 811}, {"avatar": "http://pbs.twimg.com/profile_images/586868299557920768/09W5e9Ce.jpg", "description": "Ba\u011f\u0131ms\u0131z T\u00fcrkiye Partisi (BTP) Genel Ba\u015fkan\u0131 \u2022 Resmi Twitter Hesab\u0131 \u2022 Milli Ekonomi Modeli (MEM)'in sahibi \u2022 The owner of the National Economy Model", "followers_count": 167182, "friends_count": 0, "id": 1362086456, "listed_count": 99, "location": "T\u00fcrkiye", "name": "Haydar Ba\u015f", "screen_name": "hbhaydarbas", "statuses_count": 2106}, {"avatar": "http://pbs.twimg.com/profile_images/592087312185565185/_linxTtQ.jpg", "description": "Zek\u00e2, insan\u0131n kendisi de\u011fildir. Zek\u00e2, insan\u0131n kulland\u0131\u011f\u0131 bir malzemedir. \u0130nsan g\u00f6n\u00fcld\u00fcr, g\u00f6n\u00fcl", "followers_count": 1150, "friends_count": 1457, "id": 1446889800, "listed_count": 1, "location": "Antalya", "name": "Sinan AF\u015eAR", "screen_name": "hbsinan", "statuses_count": 6363}, {"avatar": "http://pbs.twimg.com/profile_images/378800000488986464/78cb092cfd881ac82c03c382a20a5a23.jpeg", "description": "", "followers_count": 345, "friends_count": 246, "id": 1583723467, "listed_count": 0, "location": "", "name": "Engin Kaya", "screen_name": "henginkaya", "statuses_count": 516}, {"avatar": "http://pbs.twimg.com/profile_images/607674004028182528/MvNfPRQm.jpg", "description": "-Ya\u011fmur ya\u011f\u0131yor Olric. Islan\u0131yor etraf, a\u011flasak kimse anlamaz de\u011fil mi?\n-Anlamaz efendimiz..", "followers_count": 11668, "friends_count": 11589, "id": 249685730, "listed_count": 6, "location": "", "name": "H\u00fcsamettin \u00c7ALI\u015eKAN", "screen_name": "husamettince", "statuses_count": 26394}, {"avatar": "http://pbs.twimg.com/profile_images/650437036164431872/aYtehn1R.jpg", "description": "", "followers_count": 500, "friends_count": 1, "id": 308562693, "listed_count": 1, "location": "", "name": "Haydar Y\u00fccel", "screen_name": "hydrycl", "statuses_count": 1858}, {"avatar": "http://pbs.twimg.com/profile_images/607992985041666048/b7lKcK_p.jpg", "description": "\u0130nsan g\u00f6n\u00fcld\u00fcr, g\u00f6n\u00fcl. Ankara/\u0130stanbul                       Cerrahpasa Tip Fak.", "followers_count": 99, "friends_count": 117, "id": 2845917443, "listed_count": 0, "location": "", "name": "Serhan", "screen_name": "icmal_genci", "statuses_count": 140}, {"avatar": "http://pbs.twimg.com/profile_images/567420411353112576/izlphoaT.jpeg", "description": "Ba\u011f\u0131ms\u0131z T\u00fcrkiye Partisi (BTP) Bayrampa\u015fa Gen\u00e7lik Kollar\u0131'n\u0131n Resmi Twitter Hesab\u0131 https://t.co/RRLLv91Yhy", "followers_count": 600, "friends_count": 18, "id": 1551685567, "listed_count": 1, "location": "\u0130stanbul", "name": "Gen\u00e7 BTP Bayrampa\u015fa ", "screen_name": "icmalbayrampasa", "statuses_count": 624}, {"avatar": "http://pbs.twimg.com/profile_images/497669182423834624/TVMVR6YT.jpeg", "description": "T\u00fcrkiye'de maalesef dindar dedi\u011fimiz kaleler de d\u00fc\u015ft\u00fc. Tek d\u00fc\u015fmeyen kale benim \u0130CMAL GEN\u00c7L\u0130\u011e\u0130min oldu\u011fu kaledir (Prof. Dr. Haydar BA\u015e)", "followers_count": 5014, "friends_count": 137, "id": 748030224, "listed_count": 4, "location": "", "name": "\u0130cmal Gen\u00e7li\u011fi", "screen_name": "icmalgencligi", "statuses_count": 2967}, {"avatar": "http://pbs.twimg.com/profile_images/3693544686/4c1c53ed6d8f00c4d1d528115243ec98.jpeg", "description": "Makina M\u00fchendisi, Tam Ba\u011f\u0131ms\u0131z T\u00fcrkiye Taraftar\u0131", "followers_count": 513, "friends_count": 31, "id": 576545859, "listed_count": 0, "location": "\u0130stanbul", "name": "\u0130SMA\u0130L HAKKI", "screen_name": "ihmumcu", "statuses_count": 1601}, {"avatar": "http://pbs.twimg.com/profile_images/681583355012460544/txlMpUUq.jpg", "description": "G\u00fczel g\u00fcnler g\u00f6rece\u011fiz; haketti\u011fimizde! Evli-Kemalist?Sosyalist?-Hekim/Adli T\u0131p.RT ve Fav daima kat\u0131ld\u0131\u011f\u0131m anlam\u0131na gelmez!", "followers_count": 468, "friends_count": 528, "id": 463069644, "listed_count": 0, "location": "", "name": "\u0130lhan", "screen_name": "ilhanaydogdu", "statuses_count": 6672}, {"avatar": "http://pbs.twimg.com/profile_images/601388637452902400/KsdcikY1.jpg", "description": "", "followers_count": 516, "friends_count": 344, "id": 1438335606, "listed_count": 1, "location": "", "name": "\u0130nci  Ayd\u0131n Y\u0131ld\u0131r\u0131m", "screen_name": "inciyldrm89", "statuses_count": 2986}, {"avatar": "http://pbs.twimg.com/profile_images/544620931541639168/gBQiN27T.jpeg", "description": "We are dedicated for Independent Turkey - Biz Ba??ms?z bir T?rkiye i?in var?z ! Prof. Dr. Haydar Ba? - Mustafa Kemal Atat?rk", "followers_count": 2774, "friends_count": 986, "id": "1005091046", "listed_count": 2, "location": "", "name": "NeMutluT?rk?mDiyene", "screen_name": "independent_tp", "statuses_count": 4559}, {"avatar": "http://pbs.twimg.com/profile_images/611081322682019841/dWwyQ3cE.jpg", "description": "", "followers_count": 152, "friends_count": 131, "id": 2383960117, "listed_count": 1, "location": "", "name": "ismail Sancaktar", "screen_name": "ismailsalkovic", "statuses_count": 3020}, {"avatar": "http://pbs.twimg.com/profile_images/544978694108770304/nxFc9rjz.jpeg", "description": "", "followers_count": 189, "friends_count": 642, "id": 1480386817, "listed_count": 2, "location": "Eyjafjallaj\u00f6kull", "name": "Sinan G\u00fcne\u015f", "screen_name": "joseph_sinan", "statuses_count": 4591}, {"avatar": "http://pbs.twimg.com/profile_images/591545673943801856/hNN9lqlK.jpg", "description": "", "followers_count": 365, "friends_count": 477, "id": 1439687196, "listed_count": 0, "location": "", "name": "Abdulkadir G\u00f6kg\u00f6z", "screen_name": "kadiremine", "statuses_count": 3581}, {"avatar": "http://pbs.twimg.com/profile_images/661114813557420032/oYybHzz2.jpg", "description": "", "followers_count": 47, "friends_count": 26, "id": 1465898700, "listed_count": 0, "location": "", "name": "Kadir Y\u00fcceL", "screen_name": "kadiryucelll", "statuses_count": 603}, {"avatar": "http://pbs.twimg.com/profile_images/641387520991866880/Cgnk2T-R.jpg", "description": "", "followers_count": 1267, "friends_count": 154, "id": 1459798711, "listed_count": 1, "location": "", "name": "KADR\u0130YE BA\u015e HAYIR", "screen_name": "kadriyehayr", "statuses_count": 2553}, {"avatar": "http://pbs.twimg.com/profile_images/641179656595603456/S6FtSLZL.jpg", "description": "Ba\u011f\u0131ms\u0131z T\u00fcrkiye", "followers_count": 274, "friends_count": 30, "id": 456889997, "listed_count": 1, "location": "ingolstadt", "name": "mustafa tokmak", "screen_name": "kaleminkalbi", "statuses_count": 12855}, {"avatar": "http://pbs.twimg.com/profile_images/433371911423533056/C-UL2863.jpeg", "description": "Atat\u00fcrk\u00e7\u00fc, Vatansever, Ehl-i Beyt a\u015f\u0131\u011f\u0131", "followers_count": 394, "friends_count": 186, "id": 1446853927, "listed_count": 0, "location": "", "name": "g\u00fclsen karabulut", "screen_name": "karabulutglsen", "statuses_count": 1721}, {"avatar": "http://pbs.twimg.com/profile_images/578208944029614082/uXcis09U.jpeg", "description": "", "followers_count": 1130, "friends_count": 1962, "id": 572583079, "listed_count": 1, "location": "", "name": "ahmet karaguzel", "screen_name": "karaguzelcom", "statuses_count": 7932}, {"avatar": "http://pbs.twimg.com/profile_images/557513470628073472/JQ96hRU6.jpeg", "description": "son nefeste s\u00f6ylemezse bu diller b\u00fct\u00fcn kainat senin olsa ne fayda...", "followers_count": 519, "friends_count": 435, "id": 1449131708, "listed_count": 1, "location": "", "name": "\u0130lhan Ke\u00e7eci", "screen_name": "kececilhan", "statuses_count": 6650}, {"avatar": "http://pbs.twimg.com/profile_images/581183489120161793/NhBFegSx.png", "description": "", "followers_count": 744, "friends_count": 747, "id": 1225754018, "listed_count": 0, "location": "", "name": "ismail bal", "screen_name": "kesanlismail", "statuses_count": 4799}, {"avatar": "http://pbs.twimg.com/profile_images/588200224415469568/f23J2YyZ.jpg", "description": "", "followers_count": 14, "friends_count": 18, "id": 460469347, "listed_count": 0, "location": "", "name": "\u00d6nce vatan", "screen_name": "kimdineydi", "statuses_count": 1091}, {"avatar": "http://pbs.twimg.com/profile_images/654566748935581696/zYH9vgRP.jpg", "description": "", "followers_count": 376, "friends_count": 448, "id": 2801600144, "listed_count": 1, "location": "", "name": "H\u00fcseyin Kip", "screen_name": "kip_tf", "statuses_count": 1756}, {"avatar": "http://pbs.twimg.com/profile_images/669612382696677376/YRDCujp3.jpg", "description": "#Hukuk, #\u0130cmal", "followers_count": 328, "friends_count": 150, "id": 2591634631, "listed_count": 0, "location": "Kendinde", "name": "Musa Haydar", "screen_name": "krcmusahaydar", "statuses_count": 4356}, {"avatar": "http://pbs.twimg.com/profile_images/675791496109547520/aT-QEaO6.jpg", "description": "\u0130nsan G\u00f6n\u00fcld\u00fcr, G\u00f6n\u00fcl  #HB", "followers_count": 1217, "friends_count": 873, "id": 227711672, "listed_count": 1, "location": "Kayseri - Bremen", "name": "Samet KARAKAYA", "screen_name": "ksamet38", "statuses_count": 7948}, {"avatar": "http://pbs.twimg.com/profile_images/597510352377618433/ZRz0NlA7.jpg", "description": "BTP Genel Ba\u015fkan Yard\u0131mc\u0131s\u0131\nAnkarada Serbest Avukatl\u0131k yap\u0131yor", "followers_count": 1417, "friends_count": 89, "id": 1128319836, "listed_count": 0, "location": "T\u00fcrkiye/Ankara", "name": "L\u00fctfullah", "screen_name": "lutfullahonder", "statuses_count": 1176}, {"avatar": "http://pbs.twimg.com/profile_images/3673431335/da271323c239951eb28e752142a298e0.jpeg", "description": "Twitter Takip\u00e7i Artt\u0131rma : http://t.co/c5M06CkEZF", "followers_count": 167, "friends_count": 319, "id": 1436512334, "listed_count": 0, "location": "", "name": "Mehmet K\u00f6seo\u011flu", "screen_name": "m10kose", "statuses_count": 415}, {"avatar": "http://pbs.twimg.com/profile_images/549666265103876098/IjkNsPPX.jpeg", "description": "ANT\u0130EMPERYAL\u0130ST/ALLAH/PEYGAMBER/ATAT\u00dcRK/CUMHUR\u0130YET/National Economy Model/\nDM\u274c", "followers_count": 7122, "friends_count": 7008, "id": 1566680040, "listed_count": 3, "location": "Bursa", "name": "Fatma Aydemir", "screen_name": "maydemir19", "statuses_count": 10125}, {"avatar": "http://pbs.twimg.com/profile_images/3763458433/0979cd75e063aed9a36ea3b9fd903bd3.jpeg", "description": "", "followers_count": 317, "friends_count": 376, "id": 299111661, "listed_count": 4, "location": "", "name": "Mustafa \u00c7obano\u011flu", "screen_name": "mcobanoglum", "statuses_count": 10707}, {"avatar": "http://pbs.twimg.com/profile_images/663432705623896065/xHGfHBz_.png", "description": "MEDYA S\u0130YASET HABER", "followers_count": 1636, "friends_count": 1240, "id": 1028468581, "listed_count": 3, "location": "", "name": "medya siyaset", "screen_name": "medya_siyaset", "statuses_count": 448}, {"avatar": "http://pbs.twimg.com/profile_images/586234191991468033/XfGjwTzY.jpg", "description": "", "followers_count": 95, "friends_count": 7, "id": 1451114316, "listed_count": 0, "location": "", "name": "mehlika", "screen_name": "mehlikeerkii", "statuses_count": 2151}, {"avatar": "http://pbs.twimg.com/profile_images/424600374733844480/ifWuVPeh.png", "description": "Meltem Medya Grup'a ait http://t.co/DOWnQS0vL0'un resmi hesab\u0131\nhttp://t.co/fa6lrvOhxG", "followers_count": 3999, "friends_count": 3, "id": 916449361, "listed_count": 13, "location": "\u0130STANBUL", "name": "MeltemHaber.com", "screen_name": "meltemhaber", "statuses_count": 13551}, {"avatar": "http://pbs.twimg.com/profile_images/660427180531425280/mbdi08pf.jpg", "description": "National Economy Model \u2022 \u041c\u043e\u0434\u0435\u043b\u044c \u041d\u0430\u0446\u0438\u043e\u043d\u0430\u043b\u044c\u043do\u0439 \u042d\u043a\u043e\u043d\u043e\u043c\u0438\u043a\u0438 \u2022 Das Nationale Wirtschaftsmodell \u2022 Prof. Dr. Haydar Ba\u015f", "followers_count": 95108, "friends_count": 16, "id": 2340280874, "listed_count": 10, "location": "T\u00fcrkiye", "name": "Milli Ekonomi Modeli", "screen_name": "mem_hb", "statuses_count": 272}, {"avatar": "http://pbs.twimg.com/profile_images/576232804134088704/DozsJDai.jpeg", "description": "", "followers_count": 455, "friends_count": 956, "id": 292250788, "listed_count": 0, "location": "izmir ", "name": "\u00d6MER KALEM", "screen_name": "merkalem", "statuses_count": 5471}, {"avatar": "http://pbs.twimg.com/profile_images/672883799500398592/S69CLAOC.jpg", "description": "\u2764ALLAH  MUHAMMED  AL\u0130\u2764\nKuran,Ehlibeyt,Gadir-i Hum,Kerbela,Hz.Hatice,Fat\u0131ma b. Esed,Mus'ab bin Umeyr,Atat\u00fcrk,Prof.Dr. Haydar Ba\u015f,Milli Ekonomi Modeli,Btp,FB1907", "followers_count": 632, "friends_count": 235, "id": 1068823670, "listed_count": 0, "location": "Trabzon, T\u00fcrkiye", "name": "Merve AYDIN", "screen_name": "merveaydin_61", "statuses_count": 6557}, {"avatar": "http://pbs.twimg.com/profile_images/3708026372/052a899e490ce5e81e609d92b42593e7.jpeg", "description": "-- HB8613 --  @HBhaydarbas // 19.10.93*?stanbul  //  Trakyat?p*Edirne //  M.K.ATAT?RK", "followers_count": 5791, "friends_count": 4787, "id": "1432912633", "listed_count": 9, "location": "", "name": "Meryem Ke?eci", "screen_name": "meryemkcci", "statuses_count": 5117}, {"avatar": "http://pbs.twimg.com/profile_images/458945915794227200/m0Y1vLDE.jpeg", "description": "", "followers_count": 690, "friends_count": 778, "id": 269867570, "listed_count": 0, "location": "", "name": "mestabi", "screen_name": "mestozkan", "statuses_count": 4477}, {"avatar": "http://pbs.twimg.com/profile_images/510338237466820608/6a6NzJeO.jpeg", "description": "", "followers_count": 2413, "friends_count": 614, "id": 455818704, "listed_count": 2, "location": "", "name": "ADEM B\u0130R\u0130NC\u0130", "screen_name": "milletinefendi", "statuses_count": 4353}, {"avatar": "http://pbs.twimg.com/profile_images/584443468782641153/gzTH6wr4.jpg", "description": "", "followers_count": 545, "friends_count": 445, "id": 1603481498, "listed_count": 0, "location": "", "name": "mimarbayram", "screen_name": "mimarbayram", "statuses_count": 2790}, {"avatar": "http://pbs.twimg.com/profile_images/2534131417/w6h0fajo5zoqx2tdord4.jpeg", "description": "Selam olsun Ehl-i Beytle ve T\u00fcrkl\u00fc\u011f\u00fcyle gurur duyanlara! Selam olsun adaletle h\u00fckmetmi\u015f ve edecek olanlara!", "followers_count": 755, "friends_count": 636, "id": 298759864, "listed_count": 0, "location": "__", "name": "TC MNahit", "screen_name": "mnahit", "statuses_count": 3366}, {"avatar": "http://pbs.twimg.com/profile_images/378800000043276336/5fdf5ba34386d7c63b5ac1f524e5bf1f.jpeg", "description": "", "followers_count": 113, "friends_count": 566, "id": 1536755136, "listed_count": 0, "location": "", "name": "Mahmut POLAT", "screen_name": "mpmahmutpolat", "statuses_count": 1555}, {"avatar": "http://pbs.twimg.com/profile_images/610540694252462080/SU1LJ9md.jpg", "description": "Mustafa Kemal'in bir neferi ...", "followers_count": 3677, "friends_count": 3648, "id": 2186102069, "listed_count": 2, "location": "", "name": "TC# \u00d6m\u00fcr Do\u011fan #CT", "screen_name": "mrdoan7", "statuses_count": 7640}, {"avatar": "http://pbs.twimg.com/profile_images/606084831852789760/UsyUe-yR.jpg", "description": "", "followers_count": 76, "friends_count": 82, "id": 793669772, "listed_count": 0, "location": "\u0130CMAL GEN\u00c7L\u0130K  #HBA", "name": "Mustafa G\u00fcng\u00f6r", "screen_name": "mstfagngr0606", "statuses_count": 635}, {"avatar": "http://pbs.twimg.com/profile_images/656538809987932160/OAB9zRpM.jpg", "description": "", "followers_count": 276, "friends_count": 268, "id": 2183418113, "listed_count": 1, "location": "", "name": "Muhammed", "screen_name": "muhammedkkeskin", "statuses_count": 2654}, {"avatar": "http://pbs.twimg.com/profile_images/574337832082345984/ZP7HALHd.jpeg", "description": "Ustad Prof. Dr Haydar BAS in izinde olma ayricaliginda bir kul.", "followers_count": 1672, "friends_count": 824, "id": 522057394, "listed_count": 1, "location": "SakaryaTrabzonIstanbulBursa-TR", "name": "Muhammet HAYIR", "screen_name": "muhammethayir", "statuses_count": 4645}, {"avatar": "http://pbs.twimg.com/profile_images/590672847762300929/N1D7rHPS.jpg", "description": "", "followers_count": 136, "friends_count": 63, "id": 1449189181, "listed_count": 0, "location": "", "name": "M\u00fckremin G\u00f6kg\u00f6z  ", "screen_name": "mukremin1961", "statuses_count": 2538}, {"avatar": "http://pbs.twimg.com/profile_images/586233862830841856/nueIu620.jpg", "description": "BU VATAN B\u0130Z\u0130MD\u0130R B\u0130Z\u0130M KALACAK", "followers_count": 111, "friends_count": 7, "id": 1451104146, "listed_count": 0, "location": "", "name": "mustafa ", "screen_name": "mustafaerkii", "statuses_count": 2165}, {"avatar": "http://pbs.twimg.com/profile_images/2456768354/wcwv80qjnhj2gv1w9vsw.jpeg", "description": "", "followers_count": 255, "friends_count": 574, "id": 500815485, "listed_count": 0, "location": "", "name": "Mustafa Dalg\u0131\u00e7", "screen_name": "mydalgic", "statuses_count": 175}, {"avatar": "http://pbs.twimg.com/profile_images/553307494747869184/k8ZtYbDI.jpeg", "description": "Matematiksel ?spat? olmayan her ?ey uydurmad?r..", "followers_count": 1, "friends_count": 18, "id": "1218524203", "listed_count": 0, "location": "Bakmak;G?rmek demek de?ildir.", "name": "nakibudak", "screen_name": "nakibudak", "statuses_count": 19}, {"avatar": "http://pbs.twimg.com/profile_images/3713240257/84efbbfbf51215f0e153c638f8f08c5b.jpeg", "description": "", "followers_count": 334, "friends_count": 444, "id": 1443624061, "listed_count": 1, "location": "", "name": "Necla Asanoglu", "screen_name": "necla_asan", "statuses_count": 1756}, {"avatar": "http://pbs.twimg.com/profile_images/443799276477751296/6ycWztBU.jpeg", "description": "insan g\u00f6n\u00fcld\u00fcr g\u00f6n\u00fcl", "followers_count": 225, "friends_count": 440, "id": 1446897714, "listed_count": 0, "location": "HB-t\u0131p m\u0131p", "name": "nezihe kk", "screen_name": "nezihe_kk", "statuses_count": 1420}, {"avatar": "http://pbs.twimg.com/profile_images/587005215104176128/CSvu8p8a.jpg", "description": "", "followers_count": 54, "friends_count": 54, "id": 1446167329, "listed_count": 2, "location": "", "name": "nurcan \u015fahin", "screen_name": "nurcan_sahin76", "statuses_count": 8754}, {"avatar": "http://pbs.twimg.com/profile_images/378800000749597216/f8e38fe022f59e730d878172d97124fc.jpeg", "description": "Ne mutlu T\u00fcrk'\u00fcm diyene!", "followers_count": 1763, "friends_count": 1760, "id": 1447050282, "listed_count": 1, "location": "", "name": "nuri osman y\u0131lmaz", "screen_name": "nuriosmanyilmaz", "statuses_count": 5622}, {"avatar": "http://pbs.twimg.com/profile_images/588262103498285058/p8KcJaEu.jpg", "description": "Plastik Cerrahi Uzman\u0131", "followers_count": 91, "friends_count": 96, "id": 222052252, "listed_count": 0, "location": "T\u00fcrkiye", "name": "okan \u00f6zg\u00fcr \u00f6zturan", "screen_name": "okanozturan", "statuses_count": 2221}, {"avatar": "http://pbs.twimg.com/profile_images/677610954931232768/xMqqVUjc.jpg", "description": "", "followers_count": 585, "friends_count": 536, "id": 2223517721, "listed_count": 3, "location": "", "name": "\u00d6mer Taskin", "screen_name": "omertaskin42", "statuses_count": 3233}, {"avatar": "http://pbs.twimg.com/profile_images/587258288619855873/-SZGVqfX.jpg", "description": "BTP M\u0130LLETVEK\u0130L\u0130 ADAYI \u015eirket Y\u00f6netim Kurulu \u00dcyesi", "followers_count": 1847, "friends_count": 362, "id": 1083449972, "listed_count": 2, "location": "Merkez, Trabzon", "name": "\u00d6mer Turan", "screen_name": "omerturanilbey", "statuses_count": 10542}, {"avatar": "http://pbs.twimg.com/profile_images/586234520501878786/WG0U9Pau.jpg", "description": "", "followers_count": 46, "friends_count": 7, "id": 1454538062, "listed_count": 0, "location": "", "name": "osman t\u00fcfek\u00e7igil", "screen_name": "osmantfekigil", "statuses_count": 2139}, {"avatar": "http://pbs.twimg.com/profile_images/677209677437018112/W1aRFLXw.jpg", "description": "", "followers_count": 2933, "friends_count": 2712, "id": 101574133, "listed_count": 3, "location": "", "name": "Z\u00fcleyha Karaku\u015f", "screen_name": "privotcik", "statuses_count": 12401}, {"avatar": "http://pbs.twimg.com/profile_images/607858032706527232/znselcEg.jpg", "description": "", "followers_count": 194, "friends_count": 230, "id": 1444823989, "listed_count": 2, "location": "", "name": "Rahman Y\u00dcCEL", "screen_name": "rahmanyucel", "statuses_count": 6215}, {"avatar": "http://pbs.twimg.com/profile_images/584461180795752448/FYxGtfPx.jpg", "description": "", "followers_count": 230, "friends_count": 423, "id": 2518679027, "listed_count": 2, "location": "", "name": "recep parlak", "screen_name": "recepparlak10", "statuses_count": 5436}, {"avatar": "http://pbs.twimg.com/profile_images/636453079626481664/dX_RCM8u.jpg", "description": "", "followers_count": 1018, "friends_count": 1560, "id": 1446791124, "listed_count": 0, "location": "izmir t\u00fcrkiye as\u0131a", "name": "remzi karabulut", "screen_name": "remzibaba2", "statuses_count": 9611}, {"avatar": "http://pbs.twimg.com/profile_images/649950499362504704/ySOJpCca.jpg", "description": "insan g\u00f6n\u00fcld\u00fcr g\u00f6n\u00fcl", "followers_count": 220, "friends_count": 187, "id": 1446116568, "listed_count": 0, "location": "GAZ\u0130ANTEP ", "name": "DRZEYNEP EYERC\u0130O\u011eLU", "screen_name": "renantuna", "statuses_count": 607}, {"avatar": "http://pbs.twimg.com/profile_images/3609815264/3f440020a39e6f9d70e71542add63192.jpeg", "description": "", "followers_count": 473, "friends_count": 527, "id": 1231980810, "listed_count": 0, "location": "", "name": "T.C Reyhan K.o.o\u011flu", "screen_name": "reyhan_1974", "statuses_count": 4667}, {"avatar": "http://pbs.twimg.com/profile_images/578501678959312896/nUU69Lky.jpeg", "description": "", "followers_count": 1428, "friends_count": 344, "id": 1089699858, "listed_count": 0, "location": "Bas\u0131n Mensubu", "name": "Ruhi SARI", "screen_name": "rsruhisari", "statuses_count": 3227}, {"avatar": "http://pbs.twimg.com/profile_images/506152392908226561/EH4TK_DD.jpeg", "description": "", "followers_count": 55, "friends_count": 41, "id": 264951851, "listed_count": 0, "location": "", "name": "ra\u015fit bostan", "screen_name": "rstbstn", "statuses_count": 575}, {"avatar": "http://abs.twimg.com/sticky/default_profile_images/default_profile_3.png", "description": "", "followers_count": 36, "friends_count": 131, "id": 352900124, "listed_count": 0, "location": "", "name": "sahin hancer", "screen_name": "s_hancer", "statuses_count": 409}, {"avatar": "http://pbs.twimg.com/profile_images/378800000345091304/e679db750193c79eae8b6999f9cb1873.jpeg", "description": "", "followers_count": 83, "friends_count": 138, "id": 1541364150, "listed_count": 0, "location": "", "name": "salim dizi", "screen_name": "salimdizi", "statuses_count": 6170}, {"avatar": "http://pbs.twimg.com/profile_images/614201750774525952/9w154w6m.jpg", "description": "", "followers_count": 378, "friends_count": 868, "id": 1449162756, "listed_count": 0, "location": "", "name": "samioymak", "screen_name": "samioymak68", "statuses_count": 1512}, {"avatar": "http://pbs.twimg.com/profile_images/3675449637/bfc7a62e6791d1b63dec3af5cbacc210.jpeg", "description": "", "followers_count": 373, "friends_count": 325, "id": 728291760, "listed_count": 0, "location": "", "name": "Mehmet Ali Saruhan", "screen_name": "saruhan1973", "statuses_count": 2914}, {"avatar": "http://pbs.twimg.com/profile_images/3717524941/82bec06192471543fa43c8c092e2db1e.jpeg", "description": "End?stri m?hendisi. ??adam?, Ehl-i Beyt a????,Ba??ms?z T?rkiye sevdals?", "followers_count": 418, "friends_count": 235, "id": "300703997", "listed_count": 0, "location": "istanbul/T?rkiye", "name": "H.H?seyin savukduran", "screen_name": "savukduran1", "statuses_count": 935}, {"avatar": "http://pbs.twimg.com/profile_images/607567124958191616/yh6gm8OU.jpg", "description": "Ara\u015ft\u0131rmac\u0131-Yazar", "followers_count": 4291, "friends_count": 4100, "id": 462126419, "listed_count": 2, "location": "", "name": "sel\u00e7uk evsan", "screen_name": "selcukevsan", "statuses_count": 3085}, {"avatar": "http://pbs.twimg.com/profile_images/488592229695766528/0s3_FNfX.jpeg", "description": "", "followers_count": 170, "friends_count": 56, "id": 1447010402, "listed_count": 1, "location": "", "name": "Sevde Hazan", "screen_name": "sevdehazan", "statuses_count": 5483}, {"avatar": "http://pbs.twimg.com/profile_images/1862109992/23084_599508846_6436_n.jpg", "description": "", "followers_count": 544, "friends_count": 940, "id": 508669512, "listed_count": 2, "location": "", "name": "abdurrahman \u015fim\u015fek", "screen_name": "seyyah4732", "statuses_count": 7913}, {"avatar": "http://pbs.twimg.com/profile_images/583822244440363010/uQQTx_s9.jpg", "description": "@hbhaydarbas", "followers_count": 574, "friends_count": 398, "id": 180635332, "listed_count": 1, "location": ".", "name": "Seyyit ali yaman", "screen_name": "seyyitaliyaman", "statuses_count": 4724}, {"avatar": "http://pbs.twimg.com/profile_images/584675748637757440/-q6XoDPA.jpg", "description": "", "followers_count": 344, "friends_count": 330, "id": 330403370, "listed_count": 4, "location": "", "name": "B\u0130ROL SARI\u015eEN", "screen_name": "simal06", "statuses_count": 21811}, {"avatar": "http://pbs.twimg.com/profile_images/3786461234/37ccdf4fa4dd71cb8d8b13b2279884d0.jpeg", "description": "", "followers_count": 723, "friends_count": 295, "id": 1397726420, "listed_count": 0, "location": "Birimiz Hepimiz ", "name": "s\u00fcnd\u00fcz cirit", "screen_name": "snzcrt", "statuses_count": 2685}, {"avatar": "http://pbs.twimg.com/profile_images/557439852527226880/srcfUvKF.jpeg", "description": "", "followers_count": 99, "friends_count": 377, "id": 1466644399, "listed_count": 1, "location": "", "name": "Sandalc\u0131 Ailesi", "screen_name": "sonerhanife", "statuses_count": 313}, {"avatar": "http://pbs.twimg.com/profile_images/418888934899195904/obMphWus.jpeg", "description": "VATANDA\u015e", "followers_count": 28, "friends_count": 72, "id": 591259391, "listed_count": 0, "location": "", "name": "supiTURKOZ", "screen_name": "sturkoz1006", "statuses_count": 91}, {"avatar": "http://pbs.twimg.com/profile_images/378800000130024309/c102c475a59a24cb962024f6975608b6.jpeg", "description": "uzm.psikolog", "followers_count": 214, "friends_count": 278, "id": 1573763587, "listed_count": 0, "location": "", "name": "taner ta\u015f", "screen_name": "taner9182", "statuses_count": 8951}, {"avatar": "http://pbs.twimg.com/profile_images/678681556735696896/vO-yjOro.jpg", "description": "Tasar\u0131m ve proje uzman\u0131- \u0130ktisat\u00e7\u0131...      Sevdikleri : RAHMAN VE RESUL'U, Vatan, Millet, Bayrak, H\u00fcrriyet, Aile... ayr\u0131ca Milli ve g\u00fczel olan her \u015fey", "followers_count": 508, "friends_count": 372, "id": 1390463612, "listed_count": 0, "location": "ABLADA ", "name": "TC CANER YATAR", "screen_name": "tcyatar", "statuses_count": 3192}, {"avatar": "http://pbs.twimg.com/profile_images/652929224567685124/A8M9Ce18.jpg", "description": "", "followers_count": 70, "friends_count": 124, "id": 592895525, "listed_count": 0, "location": "", "name": "telman", "screen_name": "telmankahraman", "statuses_count": 492}, {"avatar": "http://pbs.twimg.com/profile_images/477443207052005376/TlW99OUK.jpeg", "description": "\u0130NSAN G\u00d6N\u00dcLD\u00dcR G\u00d6N\u00dcL", "followers_count": 338, "friends_count": 104, "id": 1453442156, "listed_count": 0, "location": "", "name": "serap tepetas", "screen_name": "tepetas_serap", "statuses_count": 1487}, {"avatar": "http://pbs.twimg.com/profile_images/658379287792365568/AjL00oic.jpg", "description": "HBA~", "followers_count": 109, "friends_count": 1033, "id": 436880124, "listed_count": 0, "location": "", "name": "Ay\u015fenur~", "screen_name": "tomyanak", "statuses_count": 1320}, {"avatar": "http://pbs.twimg.com/profile_images/590929628472156160/nSQCA_72.jpg", "description": "BASARILI KOLEJ\u0130", "followers_count": 269, "friends_count": 168, "id": 2591739619, "listed_count": 0, "location": "", "name": "TU\u011eBA KARACA", "screen_name": "tubakaraca34", "statuses_count": 2106}, {"avatar": "http://pbs.twimg.com/profile_images/520935914231439360/XjFUmfoF.jpeg", "description": "", "followers_count": 25, "friends_count": 27, "id": 2822772029, "listed_count": 1, "location": "", "name": "Nazan53", "screen_name": "tubarana4", "statuses_count": 4241}, {"avatar": "http://pbs.twimg.com/profile_images/1390454773/203457_100002323873981_6197359_n.jpg", "description": "", "followers_count": 1331, "friends_count": 135, "id": 287446886, "listed_count": 1, "location": "Trabzon", "name": "Turhan DEM\u0130R", "screen_name": "turhandemir", "statuses_count": 2551}, {"avatar": "http://pbs.twimg.com/profile_images/546707291807158272/0z9oHTDf.jpeg", "description": "Hakka ko?un, Hakkla olun, hakl? ile olun, hakl? olun, hepiniz Hakka emanet olun Prof. Dr. HAYDAR BA? - M. K. ATAT?RK", "followers_count": 484, "friends_count": 604, "id": "572213580", "listed_count": 0, "location": "", "name": "T?rk Gen?li?i #HBA", "screen_name": "turkgencligi33", "statuses_count": 967}, {"avatar": "http://pbs.twimg.com/profile_images/658929222979821568/EHt1Z-2r.jpg", "description": "Ba\u011f\u0131ms\u0131z T\u00fcrkiye Partisi, \u0130\u015f A\u015f Haydar Ba\u015f", "followers_count": 264, "friends_count": 246, "id": 1435580312, "listed_count": 0, "location": "kocaeli", "name": "Havva Uluman", "screen_name": "ulumanhavva", "statuses_count": 1726}, {"avatar": "http://pbs.twimg.com/profile_images/641945920737812481/p4vExp8P.jpg", "description": "\u0130\u015f A\u015f Haydar Ba\u015f,Ne Mutlu T\u00fcrk\u00fcm Diyene,\u0130cmal Genci,O\u011flak Burcu\u2651,Halkla \u0130li\u015fkiler..", "followers_count": 563, "friends_count": 715, "id": 2456122918, "listed_count": 0, "location": "Kocaeli", "name": "\u00dcmm\u00fchan", "screen_name": "ummuhangncsln", "statuses_count": 1923}, {"avatar": "http://pbs.twimg.com/profile_images/378800000118270144/783c92489abf314c7736250e5cc4fa28.png", "description": "", "followers_count": 4318, "friends_count": 4278, "id": 1133743956, "listed_count": 3, "location": "", "name": "yakup torun", "screen_name": "yakupsivas", "statuses_count": 20688}, {"avatar": "http://pbs.twimg.com/profile_images/672533571035406337/4ji4KhMa.jpg", "description": "TRABZON", "followers_count": 142, "friends_count": 211, "id": 1510385281, "listed_count": 0, "location": "", "name": "FERHAT YANIK", "screen_name": "yanik_ferhat", "statuses_count": 982}, {"avatar": "http://pbs.twimg.com/profile_images/553547916976324608/FVCd3Kjy.jpeg", "description": "", "followers_count": 122, "friends_count": 127, "id": 2912921447, "listed_count": 0, "location": "", "name": "Yasemin Genc", "screen_name": "yasemingenc_", "statuses_count": 140}, {"avatar": "http://pbs.twimg.com/profile_images/581198498093244416/WZpQzx1X.jpg", "description": "\u00c7ok \u015fey bilmene gerek yok...!HADD\u0130N\u0130 B\u0130L YETER...", "followers_count": 205, "friends_count": 71, "id": 1442043066, "listed_count": 0, "location": "", "name": "Yasemin Karl\u0131da\u011f", "screen_name": "yaseminkarlda", "statuses_count": 2966}, {"avatar": "http://pbs.twimg.com/profile_images/582994355377610752/YRNvCASn.jpg", "description": "14.03.1980 berlin", "followers_count": 734, "friends_count": 16, "id": 1292678210, "listed_count": 2, "location": "i\u015f a\u015f haydar ba\u015f", "name": "Yasin Y\u0131ld\u0131r\u0131m", "screen_name": "yasin140380", "statuses_count": 6200}, {"avatar": "http://pbs.twimg.com/profile_images/625672967712669696/Vu7Yyggy.jpg", "description": "Hepimiz Biriz,Karde\u015fiz", "followers_count": 2863, "friends_count": 1435, "id": 1441248848, "listed_count": 0, "location": "", "name": "Yavuz Hekimo\u011flu", "screen_name": "yavuzekm", "statuses_count": 6887}, {"avatar": "http://pbs.twimg.com/profile_images/623634208636968960/1n9igpYj.jpg", "description": "Ba\u011f\u0131ms\u0131z T\u00fcrkiye Partisi Yalova \u0130l Ba\u015fkan\u0131", "followers_count": 661, "friends_count": 126, "id": 1451558185, "listed_count": 0, "location": "Yalova", "name": "Y\u00fcksel Durak", "screen_name": "ydyuksel", "statuses_count": 885}, {"avatar": "http://pbs.twimg.com/profile_images/678304146248830977/eiByU6Cp.jpg", "description": "elektrikal elektronic and lift engineer", "followers_count": 4716, "friends_count": 100, "id": 300810562, "listed_count": 1, "location": "Malatya-\u0130stanbul", "name": "Usame Y\u0131ld\u0131z", "screen_name": "yildizusame", "statuses_count": 416}, {"avatar": "http://pbs.twimg.com/profile_images/531045281890983937/oj1FceVj.jpeg", "description": "\u064a\u0648\u0633\u0641 \u0631\u0634\u064a\u062f \u0628\u0627\u064a\u0627\u0630\u0627\u0644 bilgi@yusufresitbeyazal.com.tr", "followers_count": 3041, "friends_count": 174, "id": 1437980137, "listed_count": 1, "location": "Kerbela / \u0643\u0631\u0628\u0644\u0627\u0621", "name": "Yusuf Re\u015fit Beyazal", "screen_name": "yrbeyazal", "statuses_count": 3952}, {"avatar": "http://pbs.twimg.com/profile_images/3751564010/62c5f9ab07546f1c6a3730ff872fd5be.jpeg", "description": "", "followers_count": 551, "friends_count": 1251, "id": 1292282718, "listed_count": 1, "location": "", "name": "zehra ar\u0131soy", "screen_name": "zehraarisoy", "statuses_count": 4224}, {"avatar": "http://pbs.twimg.com/profile_images/460735865216454657/3eQ-Lfmt.jpeg", "description": null, "followers_count": 1111, "friends_count": 740, "id": "1342464319", "listed_count": 0, "location": "", "name": "Zerrin Hekimo?lu", "screen_name": "zerrinhekimoglu", "statuses_count": 4967}, {"avatar": "http://pbs.twimg.com/profile_images/3764595069/843500fd624cbe36f416f1533b176bf6.jpeg", "description": "", "followers_count": 175, "friends_count": 93, "id": 1449856447, "listed_count": 0, "location": "", "name": "zeynep ba\u015fg\u00fcden", "screen_name": "zeynepbasguden", "statuses_count": 1028}, {"avatar": "http://pbs.twimg.com/profile_images/549697327607214081/fxeghHxN.jpeg", "description": null, "followers_count": 19, "friends_count": 159, "id": "2932691885", "listed_count": 0, "location": "", "name": "?znur", "screen_name": "znur59539356", "statuses_count": 60}, {"avatar": "http://pbs.twimg.com/profile_images/528060023604543488/OJHg5I0p.jpeg", "description": "NE MUTLU T?RK?M D?YENE\r\n?? A? HAYDAR BA?\r\n@HBhaydarbas", "followers_count": 7982, "friends_count": 8435, "id": "1435153880", "listed_count": 0, "location": "", "name": "Z?ht? Kazanc?", "screen_name": "zuhtukazanci", "statuses_count": 3107}]}}