{"connections": [{"timestamp_connections": []}, {"timestamp_connections": ["emoikonomidis;karahaliosnikos;7", "elpulltrigger;mmpolyzou;1", "ysterografa;lina_papadaki;4", "pray4hou;piceboys2;1", "zdimitra1;terensquick;1", "ysterografa;terensquick;1", "ysterografa;pinelopigavra1;4", "akatsioli2012;ysterografa;4", "elpulltrigger;terensquick;1", "akatsioli2012;emoikonomidis;3", "piceboys2;terensquick;1", "o_antireporter;terensquick;1", "ysterografa;karahaliosnikos;5", "emoikonomidis;pinelopigavra1;5", "prayapp;piceboys2;2", "mairhpanagivtar;terensquick;1", "terensquick;ysterografa;1", "emoikonomidis;lina_papadaki;4", "piceboys2;mmpolyzou;1", "emoikonomidis;ysterografa;6", "hellene_in_uk;terensquick;1", "andyreportergr;terensquick;1", "prayapp;andyreportergr;1"]}, {"timestamp_connections": []}, {"timestamp_connections": []}, {"timestamp_connections": []}, {"timestamp_connections": ["terensquick;pilotirio;1", "emoikonomidis;terensquick;1", "ysterografa;papadimoulis;1", "nmarcopulos;papadimoulis;1", "ysterografa;pinelopigavra1;1", "terensquick;efremidiskosta;1", "emoikonomidis;lina_papadaki;1", "terensquick;paratiritis_thr;1", "emoikonomidis;karahaliosnikos;3", "papadimoulis;ysterografa;2", "effrosynim;papadimoulis;1", "mathraell;terensquick;1", "terensquick;newsbombgr;1", "terensquick;emoikonomidis;1", "bogdev4;terensquick;1", "andyreportergr;terensquick;1", "emoikonomidis;papadimoulis;1", "youcanalwaysbe;emoikonomidis;1", "elpulltrigger;terensquick;1", "imorakis;papadimoulis;1", "efremidiskosta;newsbombgr;1", "ysterografa;g_stathakis;1", "tribunegr;renadourou;1", "piceboys2;terensquick;1", "o_antireporter;terensquick;1", "ysterografa;renadourou;3", "emoikonomidis;pinelopigavra1;1", "prayapp;piceboys2;1", "papadimoulis;emoikonomidis;1", "terensquick;ysterografa;2", "ysterografa;lina_papadaki;1", "efremidiskosta;pilotirio;1", "emoikonomidis;g_stathakis;1", "piceboys2;mmpolyzou;3", "kostas500;terensquick;1", "emoikonomidis;renadourou;3", "elpulltrigger;mmpolyzou;3", "youcanalwaysbe;renadourou;1", "vantaraki;newsbombgr;1", "emoikonomidis;ysterografa;31", "ysterografa;karahaliosnikos;3", "prayapp;andyreportergr;1", "nmarcopulos;emoikonomidis;1", "efremidiskosta;terensquick;1"]}, {"timestamp_connections": []}, {"timestamp_connections": []}, {"timestamp_connections": []}, {"timestamp_connections": []}], "datasetInfo": {"allUsernames": [{"avatar": "http://pbs.twimg.com/profile_images/597721329329143810/bDXR0ipM.jpg", "description": "", "followers_count": 160, "friends_count": 142, "id": 3246102237, "listed_count": 8, "location": "", "name": "\u03b1\u03bb\u03b5\u03be\u03b1\u03bd\u03b4\u03c1\u03b1", "screen_name": "akatsioli2012", "statuses_count": 7981}, {"avatar": "http://pbs.twimg.com/profile_images/516629484296892416/erHVjUFs.jpeg", "description": "\u0388\u03bb\u03bb\u03b7\u03bd\u03b1\u03c2 \u03b5\u03c1\u03b3\u03ac\u03c4\u03b7\u03c2 \u03bc\u03b5 \u03c0\u03c4\u03c5\u03c7\u03af\u03bf \u03c5\u03c0\u03bf\u03c4\u03b9\u03bc\u03b7\u03bc\u03ad\u03bd\u03bf \u03b1\u03c0\u03cc \u03c4\u03b7\u03bd \u0391\u03b3\u03bf\u03c1\u03ac.\u0391\u03bd\u03c4\u03b9\u03ba\u03b1\u03c0\u03b9\u03c4\u03b1\u03bb\u03b9\u03c3\u03c4\u03ae\u03c2,\u03c0\u03b1\u03c4\u03c1\u03b9\u03ce\u03c4\u03b7\u03c2 \u03a7.\u039f  #vegan, #antispiecism #ecology #anti-nwo #antiglobalisation #antiEU", "followers_count": 1228, "friends_count": 4998, "id": 2792110739, "listed_count": 51, "location": "\u03a0\u03ad\u03c1\u03b1\u03bc\u03b1", "name": "ANDY REPORTER", "screen_name": "andyreportergr", "statuses_count": 161236}, {"avatar": "http://abs.twimg.com/sticky/default_profile_images/default_profile_3.png", "description": null, "followers_count": 189, "friends_count": 231, "id": "2288338720", "listed_count": 5, "location": "", "name": "spiros Christopoulos", "screen_name": "bogdev4", "statuses_count": 5330}, {"avatar": "http://pbs.twimg.com/profile_images/594049019048919040/EoheujHv.jpg", "description": "", "followers_count": 568, "friends_count": 591, "id": 2870193709, "listed_count": 3, "location": "", "name": "Effrosyni m", "screen_name": "effrosynim", "statuses_count": 2908}, {"avatar": "http://pbs.twimg.com/profile_images/644890557819559936/nwAMoeIa.jpg", "description": "", "followers_count": 76, "friends_count": 127, "id": 252497117, "listed_count": 1, "location": "Thessaloniki Greece", "name": "Kostas Ef.", "screen_name": "efremidiskosta", "statuses_count": 52}, {"avatar": "http://pbs.twimg.com/profile_images/535575161009750016/iJ-ceo3I.jpeg", "description": "\u03b1\u03bd\u03b1\u03b3\u03b5\u03bd\u03bd\u03b7\u03bc\u03ad\u03bd\u03b7 \u03a7\u03c1\u03b9\u03c3\u03c4\u03b9\u03b1\u03bd\u03ae \u03c0\u03bf\u03c5 \u03c4\u03b7\u03bd \u03c7\u03c4\u03cd\u03c0\u03b7\u03c3\u03b5 \u03b7 \u03ba\u03c1\u03af\u03c3\u03b7.\u03a3\u03c0\u03bf\u03c5\u03b4\u03ac\u03b6\u03c9 \u03b1\u03c3\u03c4\u03c1\u03bf\u03bb\u03bf\u03b3\u03af\u03b1,\u03bf\u03bc\u03bf\u03b9\u03bf\u03c0\u03b1\u03b8\u03b7\u03c4\u03b9\u03ba\u03ae,\u03b1\u03c0\u03cc\u03ba\u03c1\u03c5\u03c6\u03b5\u03c2 \u03b5\u03c0\u03b9\u03c3\u03c4\u03ae\u03bc\u03b5\u03c2.\u0391\u03bd\u03c4\u03b9\u03bd\u03b5\u03bf\u03c4\u03b1\u03be\u03af\u03c4\u03b9\u03c3\u03b1 \u03ba\u03b1\u03b9 #vegan", "followers_count": 1108, "friends_count": 1970, "id": 1907506801, "listed_count": 46, "location": "fixmynet.in/turo.tk/I7Cp", "name": "eleniskandali", "screen_name": "elpulltrigger", "statuses_count": 563742}, {"avatar": "http://pbs.twimg.com/profile_images/640514076968394752/CDVCX_hs.jpg", "description": "\u039f\u03b9 \u03b9\u03b4\u03ad\u03b5\u03c2 \u03b5\u03af\u03bd\u03b1\u03b9 \u03b1\u03bb\u03b5\u03be\u03af\u03c3\u03c6\u03b1\u03b9\u03c1\u03b5\u03c2  http://t.co/k542DPxLmH  Political Communication, Strategy, Analysis, Campaign management, Speechwriting...  Post-journalism...", "followers_count": 3584, "friends_count": 3531, "id": 415625348, "listed_count": 43, "location": "Athens", "name": "Manos Oikonomidis", "screen_name": "emoikonomidis", "statuses_count": 89169}, {"avatar": "http://pbs.twimg.com/profile_images/563298649984073728/Ge7ZkYW-.jpeg", "description": "\u03a5\u03c0\u03bf\u03c5\u03c1\u03b3\u03cc\u03c2 \u039f\u03b9\u03ba\u03bf\u03bd\u03bf\u03bc\u03af\u03b1\u03c2, \u0391\u03bd\u03ac\u03c0\u03c4\u03c5\u03be\u03b7\u03c2 & \u03a4\u03bf\u03c5\u03c1\u03b9\u03c3\u03bc\u03bf\u03cd | \u0392\u03bf\u03c5\u03bb\u03b5\u03c5\u03c4\u03ae\u03c2 \u039d\u03bf\u03bc\u03bf\u03cd \u03a7\u03b1\u03bd\u03af\u03c9\u03bd, \u03a3\u03a5\u03a1\u0399\u0396\u0391 | \u039a\u03b1\u03b8\u03b7\u03b3\u03b7\u03c4\u03ae\u03c2 \u03a0\u03bf\u03bb\u03b9\u03c4\u03b9\u03ba\u03ae\u03c2 \u039f\u03b9\u03ba\u03bf\u03bd\u03bf\u03bc\u03af\u03b1\u03c2, \u03a0\u03b1\u03bd\u03b5\u03c0\u03b9\u03c3\u03c4\u03ae\u03bc\u03b9\u03bf \u039a\u03c1\u03ae\u03c4\u03b7\u03c2", "followers_count": 18577, "friends_count": 428, "id": 2814643357, "listed_count": 213, "location": "", "name": "\u0393\u03b9\u03ce\u03c1\u03b3\u03bf\u03c2 \u03a3\u03c4\u03b1\u03b8\u03ac\u03ba\u03b7\u03c2", "screen_name": "g_stathakis", "statuses_count": 324}, {"avatar": "http://pbs.twimg.com/profile_images/585077274774532096/1Jg3tbzM.jpg", "description": "Libertarian, Eurosceptic, Scientist. RTs are not necessarily endorsements", "followers_count": 1861, "friends_count": 1848, "id": 34557732, "listed_count": 22, "location": "England", "name": "@Hellene_in_UK", "screen_name": "hellene_in_uk", "statuses_count": 1294}, {"avatar": "http://abs.twimg.com/sticky/default_profile_images/default_profile_4.png", "description": "", "followers_count": 2, "friends_count": 22, "id": 408185866, "listed_count": 0, "location": "", "name": "IM", "screen_name": "imorakis", "statuses_count": 23}, {"avatar": "http://pbs.twimg.com/profile_images/618032264543399937/SR-redLA.jpg", "description": "", "followers_count": 1378, "friends_count": 2013, "id": 1137528692, "listed_count": 10, "location": "\u039d\u03ad\u03b1 \u039c\u03ac\u03ba\u03c1\u03b7", "name": "\u039d\u03af\u03ba\u03bf\u03c2 \u039a\u03b1\u03c1\u03b1\u03c7\u03ac\u03bb\u03b9\u03bf\u03c2", "screen_name": "karahaliosnikos", "statuses_count": 196}, {"avatar": "http://pbs.twimg.com/profile_images/620494156876492800/x3FTmCZI.jpg", "description": "", "followers_count": 374, "friends_count": 384, "id": 53421533, "listed_count": 2, "location": "\u0391\u03b8\u03ae\u03bd\u03b1", "name": "\u039a\u03ce\u03c3\u03c4\u03b1\u03c2 \u0391.", "screen_name": "kostas500", "statuses_count": 2220}, {"avatar": "http://pbs.twimg.com/profile_images/608233832005828608/j1IxqQMX.jpg", "description": "", "followers_count": 873, "friends_count": 683, "id": 3314800455, "listed_count": 10, "location": "", "name": "Lina Papadaki", "screen_name": "lina_papadaki", "statuses_count": 1047}, {"avatar": "http://pbs.twimg.com/profile_images/344513261583871283/8ec3a5db482d047e4f3777ad9a192446.jpeg", "description": "", "followers_count": 243, "friends_count": 226, "id": 1487407548, "listed_count": 1, "location": "", "name": "\u039c\u03b1\u03af\u03c1\u03b7 \u03a0\u03b1\u03bd\u03b1\u03b3\u03b9\u03c9\u03c4\u03b1\u03c1\u03ac", "screen_name": "mairhpanagivtar", "statuses_count": 1399}, {"avatar": "http://pbs.twimg.com/profile_images/462303469378883584/WvX4pfGy.jpeg", "description": "\u039c\u0391\u039a\u0395\u0394\u039f\u039d\u0399\u0391-\u0398\u03a1\u0391\u039a\u0397 \u0395\u039b\u039b\u0391\u0394\u0391 \u039c\u0391\u03a3\r\n\u03a4\u0395\u03a1\u0395\u039d\u03a3 \u039a\u039f\u03a5\u0399\u039a", "followers_count": 375, "friends_count": 268, "id": 2474385458, "listed_count": 3, "location": "", "name": "\u039c\u0391\u039a\u0395\u0394\u039f\u039d\u0399\u0391-\u0398\u03a1\u0391\u039a\u0397 \u0395\u039b\u039b\u0391", "screen_name": "mathraell", "statuses_count": 740}, {"avatar": "http://pbs.twimg.com/profile_images/665995249047744514/ry3ivll-.jpg", "description": "The only thing that matters is loyalty. Without it you end up to be alone \u2022 Interior Design - Project Management \u2022 Facebook: MARIA POLYZOU", "followers_count": 2274, "friends_count": 2059, "id": 313319609, "listed_count": 45, "location": "Volos - Greece", "name": "maria polyzou", "screen_name": "mmpolyzou", "statuses_count": 47793}, {"avatar": "http://pbs.twimg.com/profile_images/527408728056676353/tMFW4GEE.jpeg", "description": "Newsbomb.gr : \u0393\u03b9\u03b1 \u03bd\u03b1 \u03b3\u03bd\u03c9\u03c1\u03af\u03b6\u03b5\u03c4\u03b5 \u03b1\u03bc\u03ad\u03c3\u03c9\u03c2 \u03cc,\u03c4\u03b9 \u03c3\u03ba\u03ac\u03b5\u03b9!", "followers_count": 45305, "friends_count": 456, "id": 200034893, "listed_count": 405, "location": "", "name": "newsbomb.gr", "screen_name": "newsbombgr", "statuses_count": 200748}, {"avatar": "http://pbs.twimg.com/profile_images/647000858559967232/a7jOF8nP.jpg", "description": "", "followers_count": 17, "friends_count": 138, "id": 3040774109, "listed_count": 0, "location": "", "name": "Nicola Marcopulos", "screen_name": "nmarcopulos", "statuses_count": 1028}, {"avatar": "http://pbs.twimg.com/profile_images/510565476447961089/Pm6ByT5J.png", "description": "", "followers_count": 192, "friends_count": 387, "id": 2806324759, "listed_count": 20, "location": "", "name": "Andy Reporter", "screen_name": "o_antireporter", "statuses_count": 147944}, {"avatar": "http://pbs.twimg.com/profile_images/527813822388527106/jXoqG8oL.jpeg", "description": "\u0395\u03c5\u03c1\u03c9\u03b2\u03bf\u03c5\u03bb\u03b5\u03c5\u03c4\u03ae\u03c2 \u03c4\u03bf\u03c5 \u03a3\u03a5\u03a1\u0399\u0396\u0391,  \u0391\u03bd\u03c4\u03b9\u03c0\u03c1\u03cc\u03b5\u03b4\u03c1\u03bf\u03c2 \u03c4\u03bf\u03c5 \u0395\u03c5\u03c1. \u039a\u03bf\u03b9\u03bd\u03bf\u03b2\u03bf\u03c5\u03bb\u03af\u03bf\u03c5", "followers_count": 57771, "friends_count": 2714, "id": 249601317, "listed_count": 681, "location": "Athens", "name": "Dim. Papadimoulis", "screen_name": "papadimoulis", "statuses_count": 9850}, {"avatar": "http://pbs.twimg.com/profile_images/1531105806/188586_107365292676723_100002097586808_73933_6989469_n.jpg", "description": "\u039a\u03b1\u03b8\u03b7\u03bc\u03b5\u03c1\u03b9\u03bd\u03ae \u03a0\u03b1\u03bd\u03b8\u03c1\u03b1\u03ba\u03b9\u03ba\u03ae \u0395\u03c6\u03b7\u03bc\u03b5\u03c1\u03af\u03b4\u03b1  - \u00ab\u03a0\u03b1\u03c1\u03b1\u03c4\u03b7\u03c1\u03b7\u03c4\u03ae\u03c2 \u03c4\u03b7\u03c2 \u0398\u03c1\u03ac\u03ba\u03b7\u03c2\u00bb\r\n/ \u0395\u03ba\u03b4\u03cc\u03c3\u03b5\u03b9\u03c2 - \u00ab\u03a0\u03b1\u03c1\u03b1\u03c4\u03b7\u03c1\u03b7\u03c4\u03ae\u03c2 \u0398\u03c1\u03ac\u03ba\u03b7\u03c2\u00bb", "followers_count": 2363, "friends_count": 2050, "id": 368819032, "listed_count": 35, "location": "\u039a\u03bf\u03bc\u03bf\u03c4\u03b7\u03bd\u03ae", "name": "\u03a0\u03b1\u03c1\u03b1\u03c4\u03b7\u03c1\u03b7\u03c4\u03ae\u03c2\u03a4\u03b7\u03c2\u0398\u03c1\u03ac\u03ba\u03b7\u03c2", "screen_name": "paratiritis_thr", "statuses_count": 19432}, {"avatar": "http://pbs.twimg.com/profile_images/499494831568064512/3G5DCXJ5.jpeg", "description": "E\u03bb\u03bb\u03b7\u03bd\u03cc\u03c0\u03bf\u03c5\u03bb\u03b1 \u03bc\u03b5\u03c4\u03b1\u03bd\u03ac\u03c3\u03c4\u03b5\u03c2 3\u03b7\u03c2 \u03b3\u03b5\u03bd\u03b9\u03ac\u03c2,\u03c0\u03c1\u03cc\u03c3\u03c6\u03b1\u03c4\u03b1 \u03b1\u03bd\u03b1\u03ba\u03b1\u03bb\u03cd\u03c8\u03b1\u03bc\u03b5 \u0395\u03bb\u03bb\u03b7\u03bd\u03b9\u03ba\u03ae \u03b7\u03bc\u03ce\u03bd \u03ba\u03b1\u03c4\u03b1\u03b3\u03c9\u03b3\u03ae \u03ba\u03b1\u03b9 \u03c4\u03b7\u03bd \u03bf\u03c1\u03b8\u03bf\u03b4\u03bf\u03be\u03af\u03b1.\u0394\u03b5\u03cd\u03c4\u03b5\u03c1\u03bf\u03c2 \u03bb\u03bf\u03b3\u03b1\u03c1\u03b9\u03b1\u03c3\u03bc\u03cc\u03c2 \u03b3\u03b9\u03b1\u03c4\u03af https://t.co/AySRX9GjKP", "followers_count": 1355, "friends_count": 3191, "id": 2341175431, "listed_count": 120, "location": "", "name": "Pice Boys", "screen_name": "piceboys2", "statuses_count": 286349}, {"avatar": "http://pbs.twimg.com/profile_images/2437786303/mgonbjt0buvg5tnfsclw.jpeg", "description": "ex B747& A340 OA Captain, ex Chief F.O.I. and SAFA Inspector HCAA, present CEO & Accountable Manager AM Jet Executive S.A.", "followers_count": 344, "friends_count": 282, "id": 286261094, "listed_count": 5, "location": "Glyfada", "name": "konstantinos", "screen_name": "pilotirio", "statuses_count": 27977}, {"avatar": "http://pbs.twimg.com/profile_images/518672763842985984/6vL5NTms.jpeg", "description": "\u0394\u03b7\u03bc\u03bf\u03c3\u03b9\u03bf\u03b3\u03c1\u03ac\u03c6\u03bf\u03c2", "followers_count": 1976, "friends_count": 263, "id": 407197161, "listed_count": 34, "location": "", "name": "pinelopigavra1", "screen_name": "pinelopigavra1", "statuses_count": 499}, {"avatar": "http://pbs.twimg.com/profile_images/627127842879311872/wTFBHKIm.png", "description": "Weekly Miracle Prayer Conference Call Based Out Of Houston, TX Thurs 9PM CST. Tweet us Your Prayer Request.", "followers_count": 488, "friends_count": 181, "id": 3301962427, "listed_count": 170, "location": "Houston, TX", "name": "Miracle Prayer Call", "screen_name": "pray4hou", "statuses_count": 29441}, {"avatar": "http://pbs.twimg.com/profile_images/428835223405486080/yJBLCJ74.png", "description": "The #1 App to Pray. DOWNLOAD NOW FREE ON ANDROID AND IPHONE", "followers_count": 5077, "friends_count": 0, "id": 2318640120, "listed_count": 915, "location": "", "name": "Pray App", "screen_name": "prayapp", "statuses_count": 362491}, {"avatar": "http://pbs.twimg.com/profile_images/600295565339951104/Ur9si-5L.jpg", "description": "\u03a0\u03b5\u03c1\u03b9\u03c6\u03b5\u03c1\u03b5\u03b9\u03ac\u03c1\u03c7\u03b7\u03c2 \u0391\u03c4\u03c4\u03b9\u03ba\u03ae\u03c2", "followers_count": 48096, "friends_count": 2585, "id": 21100986, "listed_count": 516, "location": "#dourou_attiki", "name": "\u03a1\u03ad\u03bd\u03b1 \u0394\u03bf\u03cd\u03c1\u03bf\u03c5", "screen_name": "renadourou", "statuses_count": 7465}, {"avatar": "http://pbs.twimg.com/profile_images/1888456458/TERENS.PNG", "description": "\u03a5\u03c6\u03c5\u03c0\u03bf\u03c5\u03c1\u03b3\u03cc\u03c2 \u03c0\u03b1\u03c1\u03ac \u03c4\u03c9 \u03a0\u03c1\u03c9\u03b8\u03c5\u03c0\u03bf\u03c5\u03c1\u03b3\u03ce \u03ba\u03b1\u03b9 \u0395\u03c0\u03b9\u03ba\u03b5\u03c6\u03b1\u03bb\u03ae\u03c2 \u0395\u03c0\u03b9\u03ba\u03bf\u03b9\u03bd\u03c9\u03bd\u03af\u03b1\u03c2 \u0391\u039d\u0395\u039e\u0391\u03a1\u03a4\u0397\u03a4\u03a9\u039d \u0395\u039b\u039b\u0397\u039d\u03a9\u039d", "followers_count": 27626, "friends_count": 952, "id": 521225288, "listed_count": 359, "location": "", "name": "Terens Quick", "screen_name": "terensquick", "statuses_count": 11807}, {"avatar": "http://pbs.twimg.com/profile_images/423569587414634496/RbN3zYU9.jpeg", "description": "\u0395\u03b9\u03b4\u03ae\u03c3\u03b5\u03b9\u03c2, \u0391\u03c0\u03cc\u03c8\u03b5\u03b9\u03c2, \u0393\u03bd\u03ce\u03bc\u03b5\u03c2, \u0395\u03bb\u03b5\u03cd\u03b8\u03b5\u03c1\u03bf \u0392\u03ae\u03bc\u03b1", "followers_count": 4233, "friends_count": 208, "id": 2237999076, "listed_count": 43, "location": "\u0391\u03b8\u03ae\u03bd\u03b1", "name": "tribune", "screen_name": "tribunegr", "statuses_count": 44434}, {"avatar": "http://pbs.twimg.com/profile_images/677680189124575233/I9EDgTvb.jpg", "description": "Art lover, journalist, breaking chains, what's meant to be will always find a way", "followers_count": 1076, "friends_count": 1666, "id": 340493784, "listed_count": 41, "location": "Athens-Greece", "name": "Irene Vantaraki", "screen_name": "vantaraki", "statuses_count": 11223}, {"avatar": "http://pbs.twimg.com/profile_images/619862475832471552/weysm2RY.jpg", "description": "", "followers_count": 233, "friends_count": 316, "id": 3368980324, "listed_count": 4, "location": "Athens ", "name": "Nikos Maltezos", "screen_name": "youcanalwaysbe", "statuses_count": 4302}, {"avatar": "http://pbs.twimg.com/profile_images/639871323972481024/yskG7D_x.png", "description": "We've come too far to turn back now...", "followers_count": 3355, "friends_count": 548, "id": 791389201, "listed_count": 90, "location": "Athens", "name": "Ysterografa", "screen_name": "ysterografa", "statuses_count": 133126}, {"avatar": "http://abs.twimg.com/sticky/default_profile_images/default_profile_1.png", "description": "", "followers_count": 20, "friends_count": 144, "id": 2876111589, "listed_count": 2, "location": "", "name": "\u0394\u03ae\u03bc\u03b7\u03c4\u03c1\u03b1", "screen_name": "zdimitra1", "statuses_count": 532}]}}